{
  "metadata" : {
    "identifier" : "https://www.nettruyenio.com/truyen-tranh/sao-gio-day-thuyen-toi-muon-yeu-325850",
    "title" : "Sao Giờ, Đẩy Thuyền Tới Muốn Yêu - Chapter 27",
    "subtitle" : null,
    "author" : null,
    "narrator" : null,
    "language" : "vi",
    "description" : null,
    "publisher" : "N/A",
    "subject" : null,
    "modified" : null,
    "published" : "2023-08-24",
    "duration" : 0,
    "abridged" : false,
    "conformsTo" : "https://readium.org/webpub-manifest/profiles/divina",
    "numberOfPages" : 79,
    "readingProgression" : "ttb",
    "belongsTo" : null,
    "presentation" : {
      "fit" : "width",
      "overflow" : "scrolled",
      "continuous" : true
    },
    "@type" : null,
    "schema:license" : null
  },
  "links" : [ {
    "rel" : "self",
    "href" : "https://raw.githubusercontent.com/thuvienonline40/book_storage_collection/main/comic_manifest.json",
    "type" : "application/divina+json"
  } ],
  "readingOrder" : [ {
    "href" : "https://raw.githubusercontent.com/tsvhcomic22/comic_storage2/main/IMAGE/IMAGE_447ad0b6e1645b994b4573eeef5bb355_59513b6b226542b12cc7055f60c9a9f0_d07a207711af274b9216a5a72bd5ee91.jpg",
    "type" : "image/jpeg",
    "bitrate" : 0,
    "duration" : 0,
    "title" : null,
    "properties" : null,
    "alternate" : [ {
      "href" : "https://i338.ntcdntempv3.com/data/images/32585/775042/001.jpg?data=net",
      "type" : "image/jpeg",
      "bitrate" : 0,
      "duration" : 0,
      "title" : null,
      "properties" : null,
      "alternate" : null
    } ]
  }, {
    "href" : "https://raw.githubusercontent.com/tsvhcomic22/comic_storage2/main/IMAGE/IMAGE_447ad0b6e1645b994b4573eeef5bb355_59513b6b226542b12cc7055f60c9a9f0_d21134577dbf99eb3f06056ec703e423.jpg",
    "type" : "image/jpeg",
    "bitrate" : 0,
    "duration" : 0,
    "title" : null,
    "properties" : null,
    "alternate" : [ {
      "href" : "https://i338.ntcdntempv3.com/data/images/32585/775042/002.jpg?data=net",
      "type" : "image/jpeg",
      "bitrate" : 0,
      "duration" : 0,
      "title" : null,
      "properties" : null,
      "alternate" : null
    } ]
  }, {
    "href" : "https://raw.githubusercontent.com/tsvhcomic22/comic_storage2/main/IMAGE/IMAGE_447ad0b6e1645b994b4573eeef5bb355_59513b6b226542b12cc7055f60c9a9f0_ea1e87f638fda0fb0c4f8edb6599fa84.jpg",
    "type" : "image/jpeg",
    "bitrate" : 0,
    "duration" : 0,
    "title" : null,
    "properties" : null,
    "alternate" : [ {
      "href" : "https://i338.ntcdntempv3.com/data/images/32585/775042/003.jpg?data=net",
      "type" : "image/jpeg",
      "bitrate" : 0,
      "duration" : 0,
      "title" : null,
      "properties" : null,
      "alternate" : null
    } ]
  }, {
    "href" : "https://raw.githubusercontent.com/tsvhcomic22/comic_storage2/main/IMAGE/IMAGE_447ad0b6e1645b994b4573eeef5bb355_59513b6b226542b12cc7055f60c9a9f0_a7424b0f7f10543df734c0a44582b27b.jpg",
    "type" : "image/jpeg",
    "bitrate" : 0,
    "duration" : 0,
    "title" : null,
    "properties" : null,
    "alternate" : [ {
      "href" : "https://i338.ntcdntempv3.com/data/images/32585/775042/004.jpg?data=net",
      "type" : "image/jpeg",
      "bitrate" : 0,
      "duration" : 0,
      "title" : null,
      "properties" : null,
      "alternate" : null
    } ]
  }, {
    "href" : "https://raw.githubusercontent.com/tsvhcomic22/comic_storage2/main/IMAGE/IMAGE_447ad0b6e1645b994b4573eeef5bb355_59513b6b226542b12cc7055f60c9a9f0_17bc05b52ac8b6760fb5cc8e6f126e1f.jpg",
    "type" : "image/jpeg",
    "bitrate" : 0,
    "duration" : 0,
    "title" : null,
    "properties" : null,
    "alternate" : [ {
      "href" : "https://i338.ntcdntempv3.com/data/images/32585/775042/005.jpg?data=net",
      "type" : "image/jpeg",
      "bitrate" : 0,
      "duration" : 0,
      "title" : null,
      "properties" : null,
      "alternate" : null
    } ]
  }, {
    "href" : "https://raw.githubusercontent.com/tsvhcomic22/comic_storage2/main/IMAGE/IMAGE_447ad0b6e1645b994b4573eeef5bb355_59513b6b226542b12cc7055f60c9a9f0_d790f4824a2e775833b711bf1f862938.jpg",
    "type" : "image/jpeg",
    "bitrate" : 0,
    "duration" : 0,
    "title" : null,
    "properties" : null,
    "alternate" : [ {
      "href" : "https://i338.ntcdntempv3.com/data/images/32585/775042/006.jpg?data=net",
      "type" : "image/jpeg",
      "bitrate" : 0,
      "duration" : 0,
      "title" : null,
      "properties" : null,
      "alternate" : null
    } ]
  }, {
    "href" : "https://raw.githubusercontent.com/tsvhcomic22/comic_storage2/main/IMAGE/IMAGE_447ad0b6e1645b994b4573eeef5bb355_59513b6b226542b12cc7055f60c9a9f0_269289ed79b9e9df6abc8c3a9ec9f4b2.jpg",
    "type" : "image/jpeg",
    "bitrate" : 0,
    "duration" : 0,
    "title" : null,
    "properties" : null,
    "alternate" : [ {
      "href" : "https://i338.ntcdntempv3.com/data/images/32585/775042/007.jpg?data=net",
      "type" : "image/jpeg",
      "bitrate" : 0,
      "duration" : 0,
      "title" : null,
      "properties" : null,
      "alternate" : null
    } ]
  }, {
    "href" : "https://raw.githubusercontent.com/tsvhcomic22/comic_storage2/main/IMAGE/IMAGE_447ad0b6e1645b994b4573eeef5bb355_59513b6b226542b12cc7055f60c9a9f0_2c2f4f00b20e054fba2c5414991d018f.jpg",
    "type" : "image/jpeg",
    "bitrate" : 0,
    "duration" : 0,
    "title" : null,
    "properties" : null,
    "alternate" : [ {
      "href" : "https://i338.ntcdntempv3.com/data/images/32585/775042/008.jpg?data=net",
      "type" : "image/jpeg",
      "bitrate" : 0,
      "duration" : 0,
      "title" : null,
      "properties" : null,
      "alternate" : null
    } ]
  }, {
    "href" : "https://raw.githubusercontent.com/tsvhcomic22/comic_storage2/main/IMAGE/IMAGE_447ad0b6e1645b994b4573eeef5bb355_59513b6b226542b12cc7055f60c9a9f0_69d3a15c5c87c606021ab62d1a4eff15.jpg",
    "type" : "image/jpeg",
    "bitrate" : 0,
    "duration" : 0,
    "title" : null,
    "properties" : null,
    "alternate" : [ {
      "href" : "https://i338.ntcdntempv3.com/data/images/32585/775042/009.jpg?data=net",
      "type" : "image/jpeg",
      "bitrate" : 0,
      "duration" : 0,
      "title" : null,
      "properties" : null,
      "alternate" : null
    } ]
  }, {
    "href" : "https://raw.githubusercontent.com/tsvhcomic22/comic_storage2/main/IMAGE/IMAGE_447ad0b6e1645b994b4573eeef5bb355_59513b6b226542b12cc7055f60c9a9f0_6f192f8b5147f57416e13f22c78eeacf.jpg",
    "type" : "image/jpeg",
    "bitrate" : 0,
    "duration" : 0,
    "title" : null,
    "properties" : null,
    "alternate" : [ {
      "href" : "https://i338.ntcdntempv3.com/data/images/32585/775042/010.jpg?data=net",
      "type" : "image/jpeg",
      "bitrate" : 0,
      "duration" : 0,
      "title" : null,
      "properties" : null,
      "alternate" : null
    } ]
  }, {
    "href" : "https://raw.githubusercontent.com/tsvhcomic22/comic_storage2/main/IMAGE/IMAGE_447ad0b6e1645b994b4573eeef5bb355_59513b6b226542b12cc7055f60c9a9f0_d326a4284a876d81f353b22aaaf6d688.jpg",
    "type" : "image/jpeg",
    "bitrate" : 0,
    "duration" : 0,
    "title" : null,
    "properties" : null,
    "alternate" : [ {
      "href" : "https://i338.ntcdntempv3.com/data/images/32585/775042/011.jpg?data=net",
      "type" : "image/jpeg",
      "bitrate" : 0,
      "duration" : 0,
      "title" : null,
      "properties" : null,
      "alternate" : null
    } ]
  }, {
    "href" : "https://raw.githubusercontent.com/tsvhcomic22/comic_storage2/main/IMAGE/IMAGE_447ad0b6e1645b994b4573eeef5bb355_59513b6b226542b12cc7055f60c9a9f0_934002f1ab25d9ac248500f408fbde8b.jpg",
    "type" : "image/jpeg",
    "bitrate" : 0,
    "duration" : 0,
    "title" : null,
    "properties" : null,
    "alternate" : [ {
      "href" : "https://i338.ntcdntempv3.com/data/images/32585/775042/012.jpg?data=net",
      "type" : "image/jpeg",
      "bitrate" : 0,
      "duration" : 0,
      "title" : null,
      "properties" : null,
      "alternate" : null
    } ]
  }, {
    "href" : "https://raw.githubusercontent.com/tsvhcomic22/comic_storage2/main/IMAGE/IMAGE_447ad0b6e1645b994b4573eeef5bb355_59513b6b226542b12cc7055f60c9a9f0_8c3fc8e1af333a5a56f273d024d0b557.jpg",
    "type" : "image/jpeg",
    "bitrate" : 0,
    "duration" : 0,
    "title" : null,
    "properties" : null,
    "alternate" : [ {
      "href" : "https://i338.ntcdntempv3.com/data/images/32585/775042/013.jpg?data=net",
      "type" : "image/jpeg",
      "bitrate" : 0,
      "duration" : 0,
      "title" : null,
      "properties" : null,
      "alternate" : null
    } ]
  }, {
    "href" : "https://raw.githubusercontent.com/tsvhcomic22/comic_storage2/main/IMAGE/IMAGE_447ad0b6e1645b994b4573eeef5bb355_59513b6b226542b12cc7055f60c9a9f0_c5c121344ffcca407d19d7f9d9f8e499.jpg",
    "type" : "image/jpeg",
    "bitrate" : 0,
    "duration" : 0,
    "title" : null,
    "properties" : null,
    "alternate" : [ {
      "href" : "https://i338.ntcdntempv3.com/data/images/32585/775042/014.jpg?data=net",
      "type" : "image/jpeg",
      "bitrate" : 0,
      "duration" : 0,
      "title" : null,
      "properties" : null,
      "alternate" : null
    } ]
  }, {
    "href" : "https://raw.githubusercontent.com/tsvhcomic22/comic_storage2/main/IMAGE/IMAGE_447ad0b6e1645b994b4573eeef5bb355_59513b6b226542b12cc7055f60c9a9f0_a05338cc1aa6c8f60e701bc9ea506f5b.jpg",
    "type" : "image/jpeg",
    "bitrate" : 0,
    "duration" : 0,
    "title" : null,
    "properties" : null,
    "alternate" : [ {
      "href" : "https://i338.ntcdntempv3.com/data/images/32585/775042/015.jpg?data=net",
      "type" : "image/jpeg",
      "bitrate" : 0,
      "duration" : 0,
      "title" : null,
      "properties" : null,
      "alternate" : null
    } ]
  }, {
    "href" : "https://raw.githubusercontent.com/tsvhcomic22/comic_storage2/main/IMAGE/IMAGE_447ad0b6e1645b994b4573eeef5bb355_59513b6b226542b12cc7055f60c9a9f0_2fa806506e537503ea4b2962b0ce5f6c.jpg",
    "type" : "image/jpeg",
    "bitrate" : 0,
    "duration" : 0,
    "title" : null,
    "properties" : null,
    "alternate" : [ {
      "href" : "https://i338.ntcdntempv3.com/data/images/32585/775042/016.jpg?data=net",
      "type" : "image/jpeg",
      "bitrate" : 0,
      "duration" : 0,
      "title" : null,
      "properties" : null,
      "alternate" : null
    } ]
  }, {
    "href" : "https://raw.githubusercontent.com/tsvhcomic22/comic_storage2/main/IMAGE/IMAGE_447ad0b6e1645b994b4573eeef5bb355_59513b6b226542b12cc7055f60c9a9f0_0a8a4abda79edc2c5f101009e6aeb8df.jpg",
    "type" : "image/jpeg",
    "bitrate" : 0,
    "duration" : 0,
    "title" : null,
    "properties" : null,
    "alternate" : [ {
      "href" : "https://i338.ntcdntempv3.com/data/images/32585/775042/017.jpg?data=net",
      "type" : "image/jpeg",
      "bitrate" : 0,
      "duration" : 0,
      "title" : null,
      "properties" : null,
      "alternate" : null
    } ]
  }, {
    "href" : "https://raw.githubusercontent.com/tsvhcomic22/comic_storage2/main/IMAGE/IMAGE_447ad0b6e1645b994b4573eeef5bb355_59513b6b226542b12cc7055f60c9a9f0_9b10d4b60251c63c8af88c3dde3eae07.jpg",
    "type" : "image/jpeg",
    "bitrate" : 0,
    "duration" : 0,
    "title" : null,
    "properties" : null,
    "alternate" : [ {
      "href" : "https://i338.ntcdntempv3.com/data/images/32585/775042/018.jpg?data=net",
      "type" : "image/jpeg",
      "bitrate" : 0,
      "duration" : 0,
      "title" : null,
      "properties" : null,
      "alternate" : null
    } ]
  }, {
    "href" : "https://raw.githubusercontent.com/tsvhcomic22/comic_storage2/main/IMAGE/IMAGE_447ad0b6e1645b994b4573eeef5bb355_59513b6b226542b12cc7055f60c9a9f0_b37536963ac1954e397d2073a425f23c.jpg",
    "type" : "image/jpeg",
    "bitrate" : 0,
    "duration" : 0,
    "title" : null,
    "properties" : null,
    "alternate" : [ {
      "href" : "https://i338.ntcdntempv3.com/data/images/32585/775042/019.jpg?data=net",
      "type" : "image/jpeg",
      "bitrate" : 0,
      "duration" : 0,
      "title" : null,
      "properties" : null,
      "alternate" : null
    } ]
  }, {
    "href" : "https://raw.githubusercontent.com/tsvhcomic22/comic_storage2/main/IMAGE/IMAGE_447ad0b6e1645b994b4573eeef5bb355_59513b6b226542b12cc7055f60c9a9f0_6291627fb0a3a54e7418b7843e2a9578.jpg",
    "type" : "image/jpeg",
    "bitrate" : 0,
    "duration" : 0,
    "title" : null,
    "properties" : null,
    "alternate" : [ {
      "href" : "https://i338.ntcdntempv3.com/data/images/32585/775042/020.jpg?data=net",
      "type" : "image/jpeg",
      "bitrate" : 0,
      "duration" : 0,
      "title" : null,
      "properties" : null,
      "alternate" : null
    } ]
  }, {
    "href" : "https://raw.githubusercontent.com/tsvhcomic22/comic_storage2/main/IMAGE/IMAGE_447ad0b6e1645b994b4573eeef5bb355_59513b6b226542b12cc7055f60c9a9f0_2e77071a915c1b9737d91f7b7b7103e8.jpg",
    "type" : "image/jpeg",
    "bitrate" : 0,
    "duration" : 0,
    "title" : null,
    "properties" : null,
    "alternate" : [ {
      "href" : "https://i338.ntcdntempv3.com/data/images/32585/775042/021.jpg?data=net",
      "type" : "image/jpeg",
      "bitrate" : 0,
      "duration" : 0,
      "title" : null,
      "properties" : null,
      "alternate" : null
    } ]
  }, {
    "href" : "https://raw.githubusercontent.com/tsvhcomic22/comic_storage2/main/IMAGE/IMAGE_447ad0b6e1645b994b4573eeef5bb355_59513b6b226542b12cc7055f60c9a9f0_36f2043930af5357405381a5500c55e3.jpg",
    "type" : "image/jpeg",
    "bitrate" : 0,
    "duration" : 0,
    "title" : null,
    "properties" : null,
    "alternate" : [ {
      "href" : "https://i338.ntcdntempv3.com/data/images/32585/775042/022.jpg?data=net",
      "type" : "image/jpeg",
      "bitrate" : 0,
      "duration" : 0,
      "title" : null,
      "properties" : null,
      "alternate" : null
    } ]
  }, {
    "href" : "https://raw.githubusercontent.com/tsvhcomic22/comic_storage2/main/IMAGE/IMAGE_447ad0b6e1645b994b4573eeef5bb355_59513b6b226542b12cc7055f60c9a9f0_20b5e95bbc8901ff419cb3f140ab63d5.jpg",
    "type" : "image/jpeg",
    "bitrate" : 0,
    "duration" : 0,
    "title" : null,
    "properties" : null,
    "alternate" : [ {
      "href" : "https://i338.ntcdntempv3.com/data/images/32585/775042/023.jpg?data=net",
      "type" : "image/jpeg",
      "bitrate" : 0,
      "duration" : 0,
      "title" : null,
      "properties" : null,
      "alternate" : null
    } ]
  }, {
    "href" : "https://raw.githubusercontent.com/tsvhcomic22/comic_storage2/main/IMAGE/IMAGE_447ad0b6e1645b994b4573eeef5bb355_59513b6b226542b12cc7055f60c9a9f0_3cd3ca992b6dab13d55e6e525849a18d.jpg",
    "type" : "image/jpeg",
    "bitrate" : 0,
    "duration" : 0,
    "title" : null,
    "properties" : null,
    "alternate" : [ {
      "href" : "https://i338.ntcdntempv3.com/data/images/32585/775042/024.jpg?data=net",
      "type" : "image/jpeg",
      "bitrate" : 0,
      "duration" : 0,
      "title" : null,
      "properties" : null,
      "alternate" : null
    } ]
  }, {
    "href" : "https://raw.githubusercontent.com/tsvhcomic22/comic_storage2/main/IMAGE/IMAGE_447ad0b6e1645b994b4573eeef5bb355_59513b6b226542b12cc7055f60c9a9f0_86e6590d47932a1e7fb58216fd9f8e54.jpg",
    "type" : "image/jpeg",
    "bitrate" : 0,
    "duration" : 0,
    "title" : null,
    "properties" : null,
    "alternate" : [ {
      "href" : "https://i338.ntcdntempv3.com/data/images/32585/775042/025.jpg?data=net",
      "type" : "image/jpeg",
      "bitrate" : 0,
      "duration" : 0,
      "title" : null,
      "properties" : null,
      "alternate" : null
    } ]
  }, {
    "href" : "https://raw.githubusercontent.com/tsvhcomic22/comic_storage2/main/IMAGE/IMAGE_447ad0b6e1645b994b4573eeef5bb355_59513b6b226542b12cc7055f60c9a9f0_b090b24f6167903c1d6b7fe9c4970474.jpg",
    "type" : "image/jpeg",
    "bitrate" : 0,
    "duration" : 0,
    "title" : null,
    "properties" : null,
    "alternate" : [ {
      "href" : "https://i338.ntcdntempv3.com/data/images/32585/775042/026.jpg?data=net",
      "type" : "image/jpeg",
      "bitrate" : 0,
      "duration" : 0,
      "title" : null,
      "properties" : null,
      "alternate" : null
    } ]
  }, {
    "href" : "https://raw.githubusercontent.com/tsvhcomic22/comic_storage2/main/IMAGE/IMAGE_447ad0b6e1645b994b4573eeef5bb355_59513b6b226542b12cc7055f60c9a9f0_3aa1fed98e8e6f8772e29d4aa8329530.jpg",
    "type" : "image/jpeg",
    "bitrate" : 0,
    "duration" : 0,
    "title" : null,
    "properties" : null,
    "alternate" : [ {
      "href" : "https://i338.ntcdntempv3.com/data/images/32585/775042/027.jpg?data=net",
      "type" : "image/jpeg",
      "bitrate" : 0,
      "duration" : 0,
      "title" : null,
      "properties" : null,
      "alternate" : null
    } ]
  }, {
    "href" : "https://raw.githubusercontent.com/tsvhcomic22/comic_storage2/main/IMAGE/IMAGE_447ad0b6e1645b994b4573eeef5bb355_59513b6b226542b12cc7055f60c9a9f0_87b431cc439dae4bdd3b089b568b25ef.jpg",
    "type" : "image/jpeg",
    "bitrate" : 0,
    "duration" : 0,
    "title" : null,
    "properties" : null,
    "alternate" : [ {
      "href" : "https://i338.ntcdntempv3.com/data/images/32585/775042/028.jpg?data=net",
      "type" : "image/jpeg",
      "bitrate" : 0,
      "duration" : 0,
      "title" : null,
      "properties" : null,
      "alternate" : null
    } ]
  } ],
  "toc" : null,
  "@context" : "https://readium.org/webpub-manifest/context.jsonld"
}