{
  "metadata" : {
    "identifier" : "https://www.nettruyenio.com/truyen-tranh/sao-gio-day-thuyen-toi-muon-yeu-325850",
    "title" : "Sao Giờ, Đẩy Thuyền Tới Muốn Yêu - Chapter 49",
    "subtitle" : null,
    "author" : null,
    "narrator" : null,
    "language" : "vi",
    "description" : null,
    "publisher" : "N/A",
    "subject" : null,
    "modified" : null,
    "published" : "2023-08-24",
    "duration" : 0,
    "abridged" : false,
    "conformsTo" : "https://readium.org/webpub-manifest/profiles/divina",
    "numberOfPages" : 79,
    "readingProgression" : "ttb",
    "belongsTo" : null,
    "presentation" : {
      "fit" : "width",
      "overflow" : "scrolled",
      "continuous" : true
    },
    "@type" : null,
    "schema:license" : null
  },
  "links" : [ {
    "rel" : "self",
    "href" : "https://raw.githubusercontent.com/thuvienonline40/book_storage_collection/main/comic_manifest.json",
    "type" : "application/divina+json"
  } ],
  "readingOrder" : [ {
    "href" : "https://raw.githubusercontent.com/tsvhcomic22/comic_storage2/main/IMAGE/IMAGE_447ad0b6e1645b994b4573eeef5bb355_fde42dc02b0c44ca7eac3231209f3078_9b2d180036caa73099f7d04ff3798a2c.jpg",
    "type" : "image/jpeg",
    "bitrate" : 0,
    "duration" : 0,
    "title" : null,
    "properties" : null,
    "alternate" : [ {
      "href" : "https://i333.ntcdntempv3.com/data/images/32585/916152/001-a37071c.jpg?data=net",
      "type" : "image/jpeg",
      "bitrate" : 0,
      "duration" : 0,
      "title" : null,
      "properties" : null,
      "alternate" : null
    } ]
  }, {
    "href" : "https://raw.githubusercontent.com/tsvhcomic22/comic_storage2/main/IMAGE/IMAGE_447ad0b6e1645b994b4573eeef5bb355_fde42dc02b0c44ca7eac3231209f3078_1fe55ea650fb5f8426a859a7a9e5d2af.jpg",
    "type" : "image/jpeg",
    "bitrate" : 0,
    "duration" : 0,
    "title" : null,
    "properties" : null,
    "alternate" : [ {
      "href" : "https://i333.ntcdntempv3.com/data/images/32585/916152/002-522bd75.jpg?data=net",
      "type" : "image/jpeg",
      "bitrate" : 0,
      "duration" : 0,
      "title" : null,
      "properties" : null,
      "alternate" : null
    } ]
  }, {
    "href" : "https://raw.githubusercontent.com/tsvhcomic22/comic_storage2/main/IMAGE/IMAGE_447ad0b6e1645b994b4573eeef5bb355_fde42dc02b0c44ca7eac3231209f3078_129f833e4bddd8c4e9c6c380159f60e6.jpg",
    "type" : "image/jpeg",
    "bitrate" : 0,
    "duration" : 0,
    "title" : null,
    "properties" : null,
    "alternate" : [ {
      "href" : "https://i333.ntcdntempv3.com/data/images/32585/916152/003-93fa71d.jpg?data=net",
      "type" : "image/jpeg",
      "bitrate" : 0,
      "duration" : 0,
      "title" : null,
      "properties" : null,
      "alternate" : null
    } ]
  }, {
    "href" : "https://raw.githubusercontent.com/tsvhcomic22/comic_storage2/main/IMAGE/IMAGE_447ad0b6e1645b994b4573eeef5bb355_fde42dc02b0c44ca7eac3231209f3078_b038f335f0e23460e27ac638aabea60c.jpg",
    "type" : "image/jpeg",
    "bitrate" : 0,
    "duration" : 0,
    "title" : null,
    "properties" : null,
    "alternate" : [ {
      "href" : "https://i333.ntcdntempv3.com/data/images/32585/916152/004-c2dd888.jpg?data=net",
      "type" : "image/jpeg",
      "bitrate" : 0,
      "duration" : 0,
      "title" : null,
      "properties" : null,
      "alternate" : null
    } ]
  }, {
    "href" : "https://raw.githubusercontent.com/tsvhcomic22/comic_storage2/main/IMAGE/IMAGE_447ad0b6e1645b994b4573eeef5bb355_fde42dc02b0c44ca7eac3231209f3078_2c69ecb5fb115057127d4f31a2b99378.jpg",
    "type" : "image/jpeg",
    "bitrate" : 0,
    "duration" : 0,
    "title" : null,
    "properties" : null,
    "alternate" : [ {
      "href" : "https://i333.ntcdntempv3.com/data/images/32585/916152/005-13fbcca.jpg?data=net",
      "type" : "image/jpeg",
      "bitrate" : 0,
      "duration" : 0,
      "title" : null,
      "properties" : null,
      "alternate" : null
    } ]
  }, {
    "href" : "https://raw.githubusercontent.com/tsvhcomic22/comic_storage2/main/IMAGE/IMAGE_447ad0b6e1645b994b4573eeef5bb355_fde42dc02b0c44ca7eac3231209f3078_3b758f8684e736b33c50788e22e22282.jpg",
    "type" : "image/jpeg",
    "bitrate" : 0,
    "duration" : 0,
    "title" : null,
    "properties" : null,
    "alternate" : [ {
      "href" : "https://i333.ntcdntempv3.com/data/images/32585/916152/006-c23b487.jpg?data=net",
      "type" : "image/jpeg",
      "bitrate" : 0,
      "duration" : 0,
      "title" : null,
      "properties" : null,
      "alternate" : null
    } ]
  }, {
    "href" : "https://raw.githubusercontent.com/tsvhcomic22/comic_storage2/main/IMAGE/IMAGE_447ad0b6e1645b994b4573eeef5bb355_fde42dc02b0c44ca7eac3231209f3078_05c00f6aecc492b681ca9352ef475cff.jpg",
    "type" : "image/jpeg",
    "bitrate" : 0,
    "duration" : 0,
    "title" : null,
    "properties" : null,
    "alternate" : [ {
      "href" : "https://i333.ntcdntempv3.com/data/images/32585/916152/007-9486751.jpg?data=net",
      "type" : "image/jpeg",
      "bitrate" : 0,
      "duration" : 0,
      "title" : null,
      "properties" : null,
      "alternate" : null
    } ]
  }, {
    "href" : "https://raw.githubusercontent.com/tsvhcomic22/comic_storage2/main/IMAGE/IMAGE_447ad0b6e1645b994b4573eeef5bb355_fde42dc02b0c44ca7eac3231209f3078_2c35da1ad7be82dfe684d60117d7ddbb.jpg",
    "type" : "image/jpeg",
    "bitrate" : 0,
    "duration" : 0,
    "title" : null,
    "properties" : null,
    "alternate" : [ {
      "href" : "https://i333.ntcdntempv3.com/data/images/32585/916152/008-4b81f73.jpg?data=net",
      "type" : "image/jpeg",
      "bitrate" : 0,
      "duration" : 0,
      "title" : null,
      "properties" : null,
      "alternate" : null
    } ]
  }, {
    "href" : "https://raw.githubusercontent.com/tsvhcomic22/comic_storage2/main/IMAGE/IMAGE_447ad0b6e1645b994b4573eeef5bb355_fde42dc02b0c44ca7eac3231209f3078_42f7f6481cab7995fc70ba3814925a23.jpg",
    "type" : "image/jpeg",
    "bitrate" : 0,
    "duration" : 0,
    "title" : null,
    "properties" : null,
    "alternate" : [ {
      "href" : "https://i333.ntcdntempv3.com/data/images/32585/916152/009-095a6d3.jpg?data=net",
      "type" : "image/jpeg",
      "bitrate" : 0,
      "duration" : 0,
      "title" : null,
      "properties" : null,
      "alternate" : null
    } ]
  }, {
    "href" : "https://raw.githubusercontent.com/tsvhcomic22/comic_storage2/main/IMAGE/IMAGE_447ad0b6e1645b994b4573eeef5bb355_fde42dc02b0c44ca7eac3231209f3078_23736c3ce3d99e95c2d05db7e99c40ae.jpg",
    "type" : "image/jpeg",
    "bitrate" : 0,
    "duration" : 0,
    "title" : null,
    "properties" : null,
    "alternate" : [ {
      "href" : "https://i333.ntcdntempv3.com/data/images/32585/916152/010-883b9ab.jpg?data=net",
      "type" : "image/jpeg",
      "bitrate" : 0,
      "duration" : 0,
      "title" : null,
      "properties" : null,
      "alternate" : null
    } ]
  }, {
    "href" : "https://raw.githubusercontent.com/tsvhcomic22/comic_storage2/main/IMAGE/IMAGE_447ad0b6e1645b994b4573eeef5bb355_fde42dc02b0c44ca7eac3231209f3078_d1c7f4afc2baef986d20f67e97dbd6cf.jpg",
    "type" : "image/jpeg",
    "bitrate" : 0,
    "duration" : 0,
    "title" : null,
    "properties" : null,
    "alternate" : [ {
      "href" : "https://i333.ntcdntempv3.com/data/images/32585/916152/011-7777718.jpg?data=net",
      "type" : "image/jpeg",
      "bitrate" : 0,
      "duration" : 0,
      "title" : null,
      "properties" : null,
      "alternate" : null
    } ]
  }, {
    "href" : "https://raw.githubusercontent.com/tsvhcomic22/comic_storage2/main/IMAGE/IMAGE_447ad0b6e1645b994b4573eeef5bb355_fde42dc02b0c44ca7eac3231209f3078_93d0eb0628ef466ffda8ee7e1167c52e.jpg",
    "type" : "image/jpeg",
    "bitrate" : 0,
    "duration" : 0,
    "title" : null,
    "properties" : null,
    "alternate" : [ {
      "href" : "https://i333.ntcdntempv3.com/data/images/32585/916152/012-7256876.jpg?data=net",
      "type" : "image/jpeg",
      "bitrate" : 0,
      "duration" : 0,
      "title" : null,
      "properties" : null,
      "alternate" : null
    } ]
  }, {
    "href" : "https://raw.githubusercontent.com/tsvhcomic22/comic_storage2/main/IMAGE/IMAGE_447ad0b6e1645b994b4573eeef5bb355_fde42dc02b0c44ca7eac3231209f3078_9f9521e3af25bd99317ef1248e17ff75.jpg",
    "type" : "image/jpeg",
    "bitrate" : 0,
    "duration" : 0,
    "title" : null,
    "properties" : null,
    "alternate" : [ {
      "href" : "https://i333.ntcdntempv3.com/data/images/32585/916152/013-86ac193.jpg?data=net",
      "type" : "image/jpeg",
      "bitrate" : 0,
      "duration" : 0,
      "title" : null,
      "properties" : null,
      "alternate" : null
    } ]
  }, {
    "href" : "https://raw.githubusercontent.com/tsvhcomic22/comic_storage2/main/IMAGE/IMAGE_447ad0b6e1645b994b4573eeef5bb355_fde42dc02b0c44ca7eac3231209f3078_c7dc33a66afa76929fe352d31a93994f.jpg",
    "type" : "image/jpeg",
    "bitrate" : 0,
    "duration" : 0,
    "title" : null,
    "properties" : null,
    "alternate" : [ {
      "href" : "https://i333.ntcdntempv3.com/data/images/32585/916152/014-c11e96d.jpg?data=net",
      "type" : "image/jpeg",
      "bitrate" : 0,
      "duration" : 0,
      "title" : null,
      "properties" : null,
      "alternate" : null
    } ]
  }, {
    "href" : "https://raw.githubusercontent.com/tsvhcomic22/comic_storage2/main/IMAGE/IMAGE_447ad0b6e1645b994b4573eeef5bb355_fde42dc02b0c44ca7eac3231209f3078_63c69a0c9373498b01cfd1b35a397911.jpg",
    "type" : "image/jpeg",
    "bitrate" : 0,
    "duration" : 0,
    "title" : null,
    "properties" : null,
    "alternate" : [ {
      "href" : "https://i333.ntcdntempv3.com/data/images/32585/916152/015-0d53ca2.jpg?data=net",
      "type" : "image/jpeg",
      "bitrate" : 0,
      "duration" : 0,
      "title" : null,
      "properties" : null,
      "alternate" : null
    } ]
  }, {
    "href" : "https://raw.githubusercontent.com/tsvhcomic22/comic_storage2/main/IMAGE/IMAGE_447ad0b6e1645b994b4573eeef5bb355_fde42dc02b0c44ca7eac3231209f3078_ebb656fd56ff5b5f45f5ec47a20a8c71.jpg",
    "type" : "image/jpeg",
    "bitrate" : 0,
    "duration" : 0,
    "title" : null,
    "properties" : null,
    "alternate" : [ {
      "href" : "https://i333.ntcdntempv3.com/data/images/32585/916152/016-7bfbe9a.jpg?data=net",
      "type" : "image/jpeg",
      "bitrate" : 0,
      "duration" : 0,
      "title" : null,
      "properties" : null,
      "alternate" : null
    } ]
  }, {
    "href" : "https://raw.githubusercontent.com/tsvhcomic22/comic_storage2/main/IMAGE/IMAGE_447ad0b6e1645b994b4573eeef5bb355_fde42dc02b0c44ca7eac3231209f3078_683e8e917c94e4ce3c9731cf8b34fa5c.jpg",
    "type" : "image/jpeg",
    "bitrate" : 0,
    "duration" : 0,
    "title" : null,
    "properties" : null,
    "alternate" : [ {
      "href" : "https://i333.ntcdntempv3.com/data/images/32585/916152/017-440cfee.jpg?data=net",
      "type" : "image/jpeg",
      "bitrate" : 0,
      "duration" : 0,
      "title" : null,
      "properties" : null,
      "alternate" : null
    } ]
  }, {
    "href" : "https://raw.githubusercontent.com/tsvhcomic22/comic_storage2/main/IMAGE/IMAGE_447ad0b6e1645b994b4573eeef5bb355_fde42dc02b0c44ca7eac3231209f3078_859783a8c471a6ba40f8ea2aa307d560.jpg",
    "type" : "image/jpeg",
    "bitrate" : 0,
    "duration" : 0,
    "title" : null,
    "properties" : null,
    "alternate" : [ {
      "href" : "https://i333.ntcdntempv3.com/data/images/32585/916152/018-195518a.jpg?data=net",
      "type" : "image/jpeg",
      "bitrate" : 0,
      "duration" : 0,
      "title" : null,
      "properties" : null,
      "alternate" : null
    } ]
  }, {
    "href" : "https://raw.githubusercontent.com/tsvhcomic22/comic_storage2/main/IMAGE/IMAGE_447ad0b6e1645b994b4573eeef5bb355_fde42dc02b0c44ca7eac3231209f3078_22ffdb2c6a21a5ba7ed8db15dd7d9b33.jpg",
    "type" : "image/jpeg",
    "bitrate" : 0,
    "duration" : 0,
    "title" : null,
    "properties" : null,
    "alternate" : [ {
      "href" : "https://i333.ntcdntempv3.com/data/images/32585/916152/019-30feb82.jpg?data=net",
      "type" : "image/jpeg",
      "bitrate" : 0,
      "duration" : 0,
      "title" : null,
      "properties" : null,
      "alternate" : null
    } ]
  }, {
    "href" : "https://raw.githubusercontent.com/tsvhcomic22/comic_storage2/main/IMAGE/IMAGE_447ad0b6e1645b994b4573eeef5bb355_fde42dc02b0c44ca7eac3231209f3078_e62ef9574c667c960d219daedf3abb05.jpg",
    "type" : "image/jpeg",
    "bitrate" : 0,
    "duration" : 0,
    "title" : null,
    "properties" : null,
    "alternate" : [ {
      "href" : "https://i333.ntcdntempv3.com/data/images/32585/916152/020-58a65b7.jpg?data=net",
      "type" : "image/jpeg",
      "bitrate" : 0,
      "duration" : 0,
      "title" : null,
      "properties" : null,
      "alternate" : null
    } ]
  }, {
    "href" : "https://raw.githubusercontent.com/tsvhcomic22/comic_storage2/main/IMAGE/IMAGE_447ad0b6e1645b994b4573eeef5bb355_fde42dc02b0c44ca7eac3231209f3078_09aeae83cf76e3c2c58527d381bee183.jpg",
    "type" : "image/jpeg",
    "bitrate" : 0,
    "duration" : 0,
    "title" : null,
    "properties" : null,
    "alternate" : [ {
      "href" : "https://i333.ntcdntempv3.com/data/images/32585/916152/021-faae5a7.jpg?data=net",
      "type" : "image/jpeg",
      "bitrate" : 0,
      "duration" : 0,
      "title" : null,
      "properties" : null,
      "alternate" : null
    } ]
  }, {
    "href" : "https://raw.githubusercontent.com/tsvhcomic22/comic_storage2/main/IMAGE/IMAGE_447ad0b6e1645b994b4573eeef5bb355_fde42dc02b0c44ca7eac3231209f3078_f0e2814c1505a48630b18f890653e41e.jpg",
    "type" : "image/jpeg",
    "bitrate" : 0,
    "duration" : 0,
    "title" : null,
    "properties" : null,
    "alternate" : [ {
      "href" : "https://i333.ntcdntempv3.com/data/images/32585/916152/022-0d21e89.jpg?data=net",
      "type" : "image/jpeg",
      "bitrate" : 0,
      "duration" : 0,
      "title" : null,
      "properties" : null,
      "alternate" : null
    } ]
  }, {
    "href" : "https://raw.githubusercontent.com/tsvhcomic22/comic_storage2/main/IMAGE/IMAGE_447ad0b6e1645b994b4573eeef5bb355_fde42dc02b0c44ca7eac3231209f3078_d627e8da1494d381cc767fd472182697.jpg",
    "type" : "image/jpeg",
    "bitrate" : 0,
    "duration" : 0,
    "title" : null,
    "properties" : null,
    "alternate" : [ {
      "href" : "https://i333.ntcdntempv3.com/data/images/32585/916152/023-f5c7fd8.jpg?data=net",
      "type" : "image/jpeg",
      "bitrate" : 0,
      "duration" : 0,
      "title" : null,
      "properties" : null,
      "alternate" : null
    } ]
  }, {
    "href" : "https://raw.githubusercontent.com/tsvhcomic22/comic_storage2/main/IMAGE/IMAGE_447ad0b6e1645b994b4573eeef5bb355_fde42dc02b0c44ca7eac3231209f3078_7ee0c40b5c728528d89c018fe02a631b.jpg",
    "type" : "image/jpeg",
    "bitrate" : 0,
    "duration" : 0,
    "title" : null,
    "properties" : null,
    "alternate" : [ {
      "href" : "https://i333.ntcdntempv3.com/data/images/32585/916152/024-ab7eebc.jpg?data=net",
      "type" : "image/jpeg",
      "bitrate" : 0,
      "duration" : 0,
      "title" : null,
      "properties" : null,
      "alternate" : null
    } ]
  }, {
    "href" : "https://raw.githubusercontent.com/tsvhcomic22/comic_storage2/main/IMAGE/IMAGE_447ad0b6e1645b994b4573eeef5bb355_fde42dc02b0c44ca7eac3231209f3078_f0cb5cc261306cad8237bb4473bd54b0.jpg",
    "type" : "image/jpeg",
    "bitrate" : 0,
    "duration" : 0,
    "title" : null,
    "properties" : null,
    "alternate" : [ {
      "href" : "https://i333.ntcdntempv3.com/data/images/32585/916152/025-2cc3282.jpg?data=net",
      "type" : "image/jpeg",
      "bitrate" : 0,
      "duration" : 0,
      "title" : null,
      "properties" : null,
      "alternate" : null
    } ]
  }, {
    "href" : "https://raw.githubusercontent.com/tsvhcomic22/comic_storage2/main/IMAGE/IMAGE_447ad0b6e1645b994b4573eeef5bb355_fde42dc02b0c44ca7eac3231209f3078_3d7b28eeaf514948818d7137b424d005.jpg",
    "type" : "image/jpeg",
    "bitrate" : 0,
    "duration" : 0,
    "title" : null,
    "properties" : null,
    "alternate" : [ {
      "href" : "https://i333.ntcdntempv3.com/data/images/32585/916152/026-4026035.jpg?data=net",
      "type" : "image/jpeg",
      "bitrate" : 0,
      "duration" : 0,
      "title" : null,
      "properties" : null,
      "alternate" : null
    } ]
  }, {
    "href" : "https://raw.githubusercontent.com/tsvhcomic22/comic_storage2/main/IMAGE/IMAGE_447ad0b6e1645b994b4573eeef5bb355_fde42dc02b0c44ca7eac3231209f3078_24dd2dc222f58bbdd006bd3748827083.jpg",
    "type" : "image/jpeg",
    "bitrate" : 0,
    "duration" : 0,
    "title" : null,
    "properties" : null,
    "alternate" : [ {
      "href" : "https://i333.ntcdntempv3.com/data/images/32585/916152/027-eb826eb.jpg?data=net",
      "type" : "image/jpeg",
      "bitrate" : 0,
      "duration" : 0,
      "title" : null,
      "properties" : null,
      "alternate" : null
    } ]
  }, {
    "href" : "https://raw.githubusercontent.com/tsvhcomic22/comic_storage2/main/IMAGE/IMAGE_447ad0b6e1645b994b4573eeef5bb355_fde42dc02b0c44ca7eac3231209f3078_6b20652c138df79e6b75803b41ee1500.jpg",
    "type" : "image/jpeg",
    "bitrate" : 0,
    "duration" : 0,
    "title" : null,
    "properties" : null,
    "alternate" : [ {
      "href" : "https://i333.ntcdntempv3.com/data/images/32585/916152/028-a7c1754.jpg?data=net",
      "type" : "image/jpeg",
      "bitrate" : 0,
      "duration" : 0,
      "title" : null,
      "properties" : null,
      "alternate" : null
    } ]
  }, {
    "href" : "https://raw.githubusercontent.com/tsvhcomic22/comic_storage2/main/IMAGE/IMAGE_447ad0b6e1645b994b4573eeef5bb355_fde42dc02b0c44ca7eac3231209f3078_f16679bad77b426a6d0370d50adc6939.jpg",
    "type" : "image/jpeg",
    "bitrate" : 0,
    "duration" : 0,
    "title" : null,
    "properties" : null,
    "alternate" : [ {
      "href" : "https://i333.ntcdntempv3.com/data/images/32585/916152/029-ad0985a.jpg?data=net",
      "type" : "image/jpeg",
      "bitrate" : 0,
      "duration" : 0,
      "title" : null,
      "properties" : null,
      "alternate" : null
    } ]
  }, {
    "href" : "https://raw.githubusercontent.com/tsvhcomic22/comic_storage2/main/IMAGE/IMAGE_447ad0b6e1645b994b4573eeef5bb355_fde42dc02b0c44ca7eac3231209f3078_b3d1d41206b7676ad512408700d6ee65.jpg",
    "type" : "image/jpeg",
    "bitrate" : 0,
    "duration" : 0,
    "title" : null,
    "properties" : null,
    "alternate" : [ {
      "href" : "https://i333.ntcdntempv3.com/data/images/32585/916152/030-46c74b9.jpg?data=net",
      "type" : "image/jpeg",
      "bitrate" : 0,
      "duration" : 0,
      "title" : null,
      "properties" : null,
      "alternate" : null
    } ]
  }, {
    "href" : "https://raw.githubusercontent.com/tsvhcomic22/comic_storage2/main/IMAGE/IMAGE_447ad0b6e1645b994b4573eeef5bb355_fde42dc02b0c44ca7eac3231209f3078_ad498c363dda9db324244096ce3fad34.jpg",
    "type" : "image/jpeg",
    "bitrate" : 0,
    "duration" : 0,
    "title" : null,
    "properties" : null,
    "alternate" : [ {
      "href" : "https://i333.ntcdntempv3.com/data/images/32585/916152/031-3c8218c.jpg?data=net",
      "type" : "image/jpeg",
      "bitrate" : 0,
      "duration" : 0,
      "title" : null,
      "properties" : null,
      "alternate" : null
    } ]
  }, {
    "href" : "https://raw.githubusercontent.com/tsvhcomic22/comic_storage2/main/IMAGE/IMAGE_447ad0b6e1645b994b4573eeef5bb355_fde42dc02b0c44ca7eac3231209f3078_0ad9f6fb5841f820546e88d63ced2ae1.jpg",
    "type" : "image/jpeg",
    "bitrate" : 0,
    "duration" : 0,
    "title" : null,
    "properties" : null,
    "alternate" : [ {
      "href" : "https://i333.ntcdntempv3.com/data/images/32585/916152/032-fcb4102.jpg?data=net",
      "type" : "image/jpeg",
      "bitrate" : 0,
      "duration" : 0,
      "title" : null,
      "properties" : null,
      "alternate" : null
    } ]
  }, {
    "href" : "https://raw.githubusercontent.com/tsvhcomic22/comic_storage2/main/IMAGE/IMAGE_447ad0b6e1645b994b4573eeef5bb355_fde42dc02b0c44ca7eac3231209f3078_ab2d28c5e8d9d2e3f1b16a6429f6a951.jpg",
    "type" : "image/jpeg",
    "bitrate" : 0,
    "duration" : 0,
    "title" : null,
    "properties" : null,
    "alternate" : [ {
      "href" : "https://i333.ntcdntempv3.com/data/images/32585/916152/033-f755c50.jpg?data=net",
      "type" : "image/jpeg",
      "bitrate" : 0,
      "duration" : 0,
      "title" : null,
      "properties" : null,
      "alternate" : null
    } ]
  }, {
    "href" : "https://raw.githubusercontent.com/tsvhcomic22/comic_storage2/main/IMAGE/IMAGE_447ad0b6e1645b994b4573eeef5bb355_fde42dc02b0c44ca7eac3231209f3078_6b67f080d1bcb80a3ca908604cbe8bcc.jpg",
    "type" : "image/jpeg",
    "bitrate" : 0,
    "duration" : 0,
    "title" : null,
    "properties" : null,
    "alternate" : [ {
      "href" : "https://i333.ntcdntempv3.com/data/images/32585/916152/034-4ec7391.jpg?data=net",
      "type" : "image/jpeg",
      "bitrate" : 0,
      "duration" : 0,
      "title" : null,
      "properties" : null,
      "alternate" : null
    } ]
  }, {
    "href" : "https://raw.githubusercontent.com/tsvhcomic22/comic_storage2/main/IMAGE/IMAGE_447ad0b6e1645b994b4573eeef5bb355_fde42dc02b0c44ca7eac3231209f3078_d24d1b0b79f7093c11026a072db4f900.jpg",
    "type" : "image/jpeg",
    "bitrate" : 0,
    "duration" : 0,
    "title" : null,
    "properties" : null,
    "alternate" : [ {
      "href" : "https://i333.ntcdntempv3.com/data/images/32585/916152/035-2c78c97.jpg?data=net",
      "type" : "image/jpeg",
      "bitrate" : 0,
      "duration" : 0,
      "title" : null,
      "properties" : null,
      "alternate" : null
    } ]
  }, {
    "href" : "https://raw.githubusercontent.com/tsvhcomic22/comic_storage2/main/IMAGE/IMAGE_447ad0b6e1645b994b4573eeef5bb355_fde42dc02b0c44ca7eac3231209f3078_7d165854062e04ce8b98ddeff3a215c9.jpg",
    "type" : "image/jpeg",
    "bitrate" : 0,
    "duration" : 0,
    "title" : null,
    "properties" : null,
    "alternate" : [ {
      "href" : "https://i333.ntcdntempv3.com/data/images/32585/916152/036-21532c0.jpg?data=net",
      "type" : "image/jpeg",
      "bitrate" : 0,
      "duration" : 0,
      "title" : null,
      "properties" : null,
      "alternate" : null
    } ]
  }, {
    "href" : "https://raw.githubusercontent.com/tsvhcomic22/comic_storage2/main/IMAGE/IMAGE_447ad0b6e1645b994b4573eeef5bb355_fde42dc02b0c44ca7eac3231209f3078_0d999c0b23ea750833cca908e9118d88.jpg",
    "type" : "image/jpeg",
    "bitrate" : 0,
    "duration" : 0,
    "title" : null,
    "properties" : null,
    "alternate" : [ {
      "href" : "https://i333.ntcdntempv3.com/data/images/32585/916152/037-53b3a5d.jpg?data=net",
      "type" : "image/jpeg",
      "bitrate" : 0,
      "duration" : 0,
      "title" : null,
      "properties" : null,
      "alternate" : null
    } ]
  }, {
    "href" : "https://raw.githubusercontent.com/tsvhcomic22/comic_storage2/main/IMAGE/IMAGE_447ad0b6e1645b994b4573eeef5bb355_fde42dc02b0c44ca7eac3231209f3078_070715b65d879542d16c0a52787959cd.jpg",
    "type" : "image/jpeg",
    "bitrate" : 0,
    "duration" : 0,
    "title" : null,
    "properties" : null,
    "alternate" : [ {
      "href" : "https://i333.ntcdntempv3.com/data/images/32585/916152/038-4d875da.jpg?data=net",
      "type" : "image/jpeg",
      "bitrate" : 0,
      "duration" : 0,
      "title" : null,
      "properties" : null,
      "alternate" : null
    } ]
  }, {
    "href" : "https://raw.githubusercontent.com/tsvhcomic22/comic_storage2/main/IMAGE/IMAGE_447ad0b6e1645b994b4573eeef5bb355_fde42dc02b0c44ca7eac3231209f3078_665fd5e2d151691428b0d15308fe52fb.jpg",
    "type" : "image/jpeg",
    "bitrate" : 0,
    "duration" : 0,
    "title" : null,
    "properties" : null,
    "alternate" : [ {
      "href" : "https://i333.ntcdntempv3.com/data/images/32585/916152/039-459c671.jpg?data=net",
      "type" : "image/jpeg",
      "bitrate" : 0,
      "duration" : 0,
      "title" : null,
      "properties" : null,
      "alternate" : null
    } ]
  }, {
    "href" : "https://raw.githubusercontent.com/tsvhcomic22/comic_storage2/main/IMAGE/IMAGE_447ad0b6e1645b994b4573eeef5bb355_fde42dc02b0c44ca7eac3231209f3078_15a1d65abd74b9adeba7cf7a4df85b11.jpg",
    "type" : "image/jpeg",
    "bitrate" : 0,
    "duration" : 0,
    "title" : null,
    "properties" : null,
    "alternate" : [ {
      "href" : "https://i333.ntcdntempv3.com/data/images/32585/916152/040-eebb3d0.jpg?data=net",
      "type" : "image/jpeg",
      "bitrate" : 0,
      "duration" : 0,
      "title" : null,
      "properties" : null,
      "alternate" : null
    } ]
  }, {
    "href" : "https://raw.githubusercontent.com/tsvhcomic22/comic_storage2/main/IMAGE/IMAGE_447ad0b6e1645b994b4573eeef5bb355_fde42dc02b0c44ca7eac3231209f3078_c3832c70b867c088666a781238b9ef4d.jpg",
    "type" : "image/jpeg",
    "bitrate" : 0,
    "duration" : 0,
    "title" : null,
    "properties" : null,
    "alternate" : [ {
      "href" : "https://i333.ntcdntempv3.com/data/images/32585/916152/041-92ff8b8.jpg?data=net",
      "type" : "image/jpeg",
      "bitrate" : 0,
      "duration" : 0,
      "title" : null,
      "properties" : null,
      "alternate" : null
    } ]
  }, {
    "href" : "https://raw.githubusercontent.com/tsvhcomic22/comic_storage2/main/IMAGE/IMAGE_447ad0b6e1645b994b4573eeef5bb355_fde42dc02b0c44ca7eac3231209f3078_0896cf3af086aca238cd9d465067ba2d.jpg",
    "type" : "image/jpeg",
    "bitrate" : 0,
    "duration" : 0,
    "title" : null,
    "properties" : null,
    "alternate" : [ {
      "href" : "https://i333.ntcdntempv3.com/data/images/32585/916152/042-c4bab99.jpg?data=net",
      "type" : "image/jpeg",
      "bitrate" : 0,
      "duration" : 0,
      "title" : null,
      "properties" : null,
      "alternate" : null
    } ]
  }, {
    "href" : "https://raw.githubusercontent.com/tsvhcomic22/comic_storage2/main/IMAGE/IMAGE_447ad0b6e1645b994b4573eeef5bb355_fde42dc02b0c44ca7eac3231209f3078_87607066704268739319b6e541467a56.jpg",
    "type" : "image/jpeg",
    "bitrate" : 0,
    "duration" : 0,
    "title" : null,
    "properties" : null,
    "alternate" : [ {
      "href" : "https://i333.ntcdntempv3.com/data/images/32585/916152/043-99564c7.jpg?data=net",
      "type" : "image/jpeg",
      "bitrate" : 0,
      "duration" : 0,
      "title" : null,
      "properties" : null,
      "alternate" : null
    } ]
  }, {
    "href" : "https://raw.githubusercontent.com/tsvhcomic22/comic_storage2/main/IMAGE/IMAGE_447ad0b6e1645b994b4573eeef5bb355_fde42dc02b0c44ca7eac3231209f3078_3eb00cfc4d9b7ecd7ee453bb2963f0fb.jpg",
    "type" : "image/jpeg",
    "bitrate" : 0,
    "duration" : 0,
    "title" : null,
    "properties" : null,
    "alternate" : [ {
      "href" : "https://i333.ntcdntempv3.com/data/images/32585/916152/044-0f4feef.jpg?data=net",
      "type" : "image/jpeg",
      "bitrate" : 0,
      "duration" : 0,
      "title" : null,
      "properties" : null,
      "alternate" : null
    } ]
  }, {
    "href" : "https://raw.githubusercontent.com/tsvhcomic22/comic_storage2/main/IMAGE/IMAGE_447ad0b6e1645b994b4573eeef5bb355_fde42dc02b0c44ca7eac3231209f3078_89fe9c2935c750bb11ff66062f77c2a2.jpg",
    "type" : "image/jpeg",
    "bitrate" : 0,
    "duration" : 0,
    "title" : null,
    "properties" : null,
    "alternate" : [ {
      "href" : "https://i333.ntcdntempv3.com/data/images/32585/916152/045-bee4fc0.jpg?data=net",
      "type" : "image/jpeg",
      "bitrate" : 0,
      "duration" : 0,
      "title" : null,
      "properties" : null,
      "alternate" : null
    } ]
  }, {
    "href" : "https://raw.githubusercontent.com/tsvhcomic22/comic_storage2/main/IMAGE/IMAGE_447ad0b6e1645b994b4573eeef5bb355_fde42dc02b0c44ca7eac3231209f3078_5d141f60510770449c2e76ff4bc38123.jpg",
    "type" : "image/jpeg",
    "bitrate" : 0,
    "duration" : 0,
    "title" : null,
    "properties" : null,
    "alternate" : [ {
      "href" : "https://i333.ntcdntempv3.com/data/images/32585/916152/046-0dec6db.jpg?data=net",
      "type" : "image/jpeg",
      "bitrate" : 0,
      "duration" : 0,
      "title" : null,
      "properties" : null,
      "alternate" : null
    } ]
  }, {
    "href" : "https://raw.githubusercontent.com/tsvhcomic22/comic_storage2/main/IMAGE/IMAGE_447ad0b6e1645b994b4573eeef5bb355_fde42dc02b0c44ca7eac3231209f3078_15eb2ead47904dc77e372fb8a2ed669a.jpg",
    "type" : "image/jpeg",
    "bitrate" : 0,
    "duration" : 0,
    "title" : null,
    "properties" : null,
    "alternate" : [ {
      "href" : "https://i333.ntcdntempv3.com/data/images/32585/916152/047-45e9a49.jpg?data=net",
      "type" : "image/jpeg",
      "bitrate" : 0,
      "duration" : 0,
      "title" : null,
      "properties" : null,
      "alternate" : null
    } ]
  }, {
    "href" : "https://raw.githubusercontent.com/tsvhcomic22/comic_storage2/main/IMAGE/IMAGE_447ad0b6e1645b994b4573eeef5bb355_fde42dc02b0c44ca7eac3231209f3078_054b65952fc193638912053620654c1d.jpg",
    "type" : "image/jpeg",
    "bitrate" : 0,
    "duration" : 0,
    "title" : null,
    "properties" : null,
    "alternate" : [ {
      "href" : "https://i333.ntcdntempv3.com/data/images/32585/916152/048-2a2d739.jpg?data=net",
      "type" : "image/jpeg",
      "bitrate" : 0,
      "duration" : 0,
      "title" : null,
      "properties" : null,
      "alternate" : null
    } ]
  }, {
    "href" : "https://raw.githubusercontent.com/tsvhcomic22/comic_storage2/main/IMAGE/IMAGE_447ad0b6e1645b994b4573eeef5bb355_fde42dc02b0c44ca7eac3231209f3078_f670908827348a41695e1e5114205e1a.jpg",
    "type" : "image/jpeg",
    "bitrate" : 0,
    "duration" : 0,
    "title" : null,
    "properties" : null,
    "alternate" : [ {
      "href" : "https://i333.ntcdntempv3.com/data/images/32585/916152/049-9f53191.jpg?data=net",
      "type" : "image/jpeg",
      "bitrate" : 0,
      "duration" : 0,
      "title" : null,
      "properties" : null,
      "alternate" : null
    } ]
  } ],
  "toc" : null,
  "@context" : "https://readium.org/webpub-manifest/context.jsonld"
}