{
  "metadata" : {
    "identifier" : "https://www.nettruyenio.com/truyen-tranh/co-di-ma-ket-hon-voi-chong-toi-di-547485",
    "title" : "Cô Đi Mà Kết Hôn Với Chồng Tôi Đi - Chapter 59",
    "subtitle" : null,
    "author" : null,
    "narrator" : null,
    "language" : "vi",
    "description" : null,
    "publisher" : "N/A",
    "subject" : null,
    "modified" : null,
    "published" : "2023-08-30",
    "duration" : 0,
    "abridged" : false,
    "conformsTo" : "https://readium.org/webpub-manifest/profiles/divina",
    "numberOfPages" : 76,
    "readingProgression" : "ttb",
    "belongsTo" : null,
    "presentation" : {
      "fit" : "width",
      "overflow" : "scrolled",
      "continuous" : true
    },
    "@type" : null,
    "schema:license" : null
  },
  "links" : [ {
    "rel" : "self",
    "href" : "https://raw.githubusercontent.com/thuvienonline40/book_storage_collection/main/comic_manifest.json",
    "type" : "application/divina+json"
  } ],
  "readingOrder" : [ {
    "href" : "https://raw.githubusercontent.com/quetcccd/comic_storage2/main/IMAGE/IMAGE_d25dc67eff9b71a6c22285b5e717268b_f3023977f29e7d36c64d63d6e4a460b8_0fb4f94ffc954d8b4147211f46fff884.jpg",
    "type" : "image/jpeg",
    "bitrate" : 0,
    "duration" : 0,
    "title" : null,
    "properties" : null,
    "alternate" : [ {
      "href" : "https://i115.ntcdntempv3.com/data/images/54748/927938/001-2df6b0b.jpg?data=net",
      "type" : "image/jpeg",
      "bitrate" : 0,
      "duration" : 0,
      "title" : null,
      "properties" : null,
      "alternate" : null
    } ]
  }, {
    "href" : "https://raw.githubusercontent.com/quetcccd/comic_storage2/main/IMAGE/IMAGE_d25dc67eff9b71a6c22285b5e717268b_f3023977f29e7d36c64d63d6e4a460b8_ea93455bfc6d365dddac9ba48ac85a80.jpg",
    "type" : "image/jpeg",
    "bitrate" : 0,
    "duration" : 0,
    "title" : null,
    "properties" : null,
    "alternate" : [ {
      "href" : "https://i115.ntcdntempv3.com/data/images/54748/927938/002-6c05043.jpg?data=net",
      "type" : "image/jpeg",
      "bitrate" : 0,
      "duration" : 0,
      "title" : null,
      "properties" : null,
      "alternate" : null
    } ]
  }, {
    "href" : "https://raw.githubusercontent.com/quetcccd/comic_storage2/main/IMAGE/IMAGE_d25dc67eff9b71a6c22285b5e717268b_f3023977f29e7d36c64d63d6e4a460b8_c5ca36b91ad085e22518d3164e8b9db5.jpg",
    "type" : "image/jpeg",
    "bitrate" : 0,
    "duration" : 0,
    "title" : null,
    "properties" : null,
    "alternate" : [ {
      "href" : "https://i115.ntcdntempv3.com/data/images/54748/927938/003-87be32a.jpg?data=net",
      "type" : "image/jpeg",
      "bitrate" : 0,
      "duration" : 0,
      "title" : null,
      "properties" : null,
      "alternate" : null
    } ]
  }, {
    "href" : "https://raw.githubusercontent.com/quetcccd/comic_storage2/main/IMAGE/IMAGE_d25dc67eff9b71a6c22285b5e717268b_f3023977f29e7d36c64d63d6e4a460b8_73eeb3354fb21c063933c228b047f177.jpg",
    "type" : "image/jpeg",
    "bitrate" : 0,
    "duration" : 0,
    "title" : null,
    "properties" : null,
    "alternate" : [ {
      "href" : "https://i115.ntcdntempv3.com/data/images/54748/927938/004-c216a5d.jpg?data=net",
      "type" : "image/jpeg",
      "bitrate" : 0,
      "duration" : 0,
      "title" : null,
      "properties" : null,
      "alternate" : null
    } ]
  }, {
    "href" : "https://raw.githubusercontent.com/quetcccd/comic_storage2/main/IMAGE/IMAGE_d25dc67eff9b71a6c22285b5e717268b_f3023977f29e7d36c64d63d6e4a460b8_cebe8503778db1bd20a740d35de18059.jpg",
    "type" : "image/jpeg",
    "bitrate" : 0,
    "duration" : 0,
    "title" : null,
    "properties" : null,
    "alternate" : [ {
      "href" : "https://i115.ntcdntempv3.com/data/images/54748/927938/005-2b1ce35.jpg?data=net",
      "type" : "image/jpeg",
      "bitrate" : 0,
      "duration" : 0,
      "title" : null,
      "properties" : null,
      "alternate" : null
    } ]
  }, {
    "href" : "https://raw.githubusercontent.com/quetcccd/comic_storage2/main/IMAGE/IMAGE_d25dc67eff9b71a6c22285b5e717268b_f3023977f29e7d36c64d63d6e4a460b8_aaa9f00304371aff41c5b22e4b6b78c8.jpg",
    "type" : "image/jpeg",
    "bitrate" : 0,
    "duration" : 0,
    "title" : null,
    "properties" : null,
    "alternate" : [ {
      "href" : "https://i115.ntcdntempv3.com/data/images/54748/927938/006-30fc082.jpg?data=net",
      "type" : "image/jpeg",
      "bitrate" : 0,
      "duration" : 0,
      "title" : null,
      "properties" : null,
      "alternate" : null
    } ]
  }, {
    "href" : "https://raw.githubusercontent.com/quetcccd/comic_storage2/main/IMAGE/IMAGE_d25dc67eff9b71a6c22285b5e717268b_f3023977f29e7d36c64d63d6e4a460b8_66fcec46448dfdf9ac592ff0b856bbbe.jpg",
    "type" : "image/jpeg",
    "bitrate" : 0,
    "duration" : 0,
    "title" : null,
    "properties" : null,
    "alternate" : [ {
      "href" : "https://i115.ntcdntempv3.com/data/images/54748/927938/007-bfaea5b.jpg?data=net",
      "type" : "image/jpeg",
      "bitrate" : 0,
      "duration" : 0,
      "title" : null,
      "properties" : null,
      "alternate" : null
    } ]
  }, {
    "href" : "https://raw.githubusercontent.com/quetcccd/comic_storage2/main/IMAGE/IMAGE_d25dc67eff9b71a6c22285b5e717268b_f3023977f29e7d36c64d63d6e4a460b8_6c394f0c78bf6d4c785b3ce0fd9b2710.jpg",
    "type" : "image/jpeg",
    "bitrate" : 0,
    "duration" : 0,
    "title" : null,
    "properties" : null,
    "alternate" : [ {
      "href" : "https://i115.ntcdntempv3.com/data/images/54748/927938/008-9eb68a8.jpg?data=net",
      "type" : "image/jpeg",
      "bitrate" : 0,
      "duration" : 0,
      "title" : null,
      "properties" : null,
      "alternate" : null
    } ]
  }, {
    "href" : "https://raw.githubusercontent.com/quetcccd/comic_storage2/main/IMAGE/IMAGE_d25dc67eff9b71a6c22285b5e717268b_f3023977f29e7d36c64d63d6e4a460b8_62c386329d25bc6da8e9f3cc1f96dbe5.jpg",
    "type" : "image/jpeg",
    "bitrate" : 0,
    "duration" : 0,
    "title" : null,
    "properties" : null,
    "alternate" : [ {
      "href" : "https://i115.ntcdntempv3.com/data/images/54748/927938/009-137b623.jpg?data=net",
      "type" : "image/jpeg",
      "bitrate" : 0,
      "duration" : 0,
      "title" : null,
      "properties" : null,
      "alternate" : null
    } ]
  }, {
    "href" : "https://raw.githubusercontent.com/quetcccd/comic_storage2/main/IMAGE/IMAGE_d25dc67eff9b71a6c22285b5e717268b_f3023977f29e7d36c64d63d6e4a460b8_aa6956f4270bddac18c16759f3e6a5f9.jpg",
    "type" : "image/jpeg",
    "bitrate" : 0,
    "duration" : 0,
    "title" : null,
    "properties" : null,
    "alternate" : [ {
      "href" : "https://i115.ntcdntempv3.com/data/images/54748/927938/010-b4cf2c5.jpg?data=net",
      "type" : "image/jpeg",
      "bitrate" : 0,
      "duration" : 0,
      "title" : null,
      "properties" : null,
      "alternate" : null
    } ]
  }, {
    "href" : "https://raw.githubusercontent.com/quetcccd/comic_storage2/main/IMAGE/IMAGE_d25dc67eff9b71a6c22285b5e717268b_f3023977f29e7d36c64d63d6e4a460b8_530d369b8efaf2656db22a5cf81e7e8e.jpg",
    "type" : "image/jpeg",
    "bitrate" : 0,
    "duration" : 0,
    "title" : null,
    "properties" : null,
    "alternate" : [ {
      "href" : "https://i115.ntcdntempv3.com/data/images/54748/927938/011-6a9f293.jpg?data=net",
      "type" : "image/jpeg",
      "bitrate" : 0,
      "duration" : 0,
      "title" : null,
      "properties" : null,
      "alternate" : null
    } ]
  }, {
    "href" : "https://raw.githubusercontent.com/quetcccd/comic_storage2/main/IMAGE/IMAGE_d25dc67eff9b71a6c22285b5e717268b_f3023977f29e7d36c64d63d6e4a460b8_b28702313b176efa5187c74c083b8068.jpg",
    "type" : "image/jpeg",
    "bitrate" : 0,
    "duration" : 0,
    "title" : null,
    "properties" : null,
    "alternate" : [ {
      "href" : "https://i115.ntcdntempv3.com/data/images/54748/927938/012-410f797.jpg?data=net",
      "type" : "image/jpeg",
      "bitrate" : 0,
      "duration" : 0,
      "title" : null,
      "properties" : null,
      "alternate" : null
    } ]
  }, {
    "href" : "https://raw.githubusercontent.com/quetcccd/comic_storage2/main/IMAGE/IMAGE_d25dc67eff9b71a6c22285b5e717268b_f3023977f29e7d36c64d63d6e4a460b8_c16fb1e2ffe80d436b8f2b66b90d9ef4.jpg",
    "type" : "image/jpeg",
    "bitrate" : 0,
    "duration" : 0,
    "title" : null,
    "properties" : null,
    "alternate" : [ {
      "href" : "https://i115.ntcdntempv3.com/data/images/54748/927938/013-f37f424.jpg?data=net",
      "type" : "image/jpeg",
      "bitrate" : 0,
      "duration" : 0,
      "title" : null,
      "properties" : null,
      "alternate" : null
    } ]
  }, {
    "href" : "https://raw.githubusercontent.com/quetcccd/comic_storage2/main/IMAGE/IMAGE_d25dc67eff9b71a6c22285b5e717268b_f3023977f29e7d36c64d63d6e4a460b8_76b6c692723f469a8b273d89df84a546.jpg",
    "type" : "image/jpeg",
    "bitrate" : 0,
    "duration" : 0,
    "title" : null,
    "properties" : null,
    "alternate" : [ {
      "href" : "https://i115.ntcdntempv3.com/data/images/54748/927938/014-d07c178.jpg?data=net",
      "type" : "image/jpeg",
      "bitrate" : 0,
      "duration" : 0,
      "title" : null,
      "properties" : null,
      "alternate" : null
    } ]
  }, {
    "href" : "https://raw.githubusercontent.com/quetcccd/comic_storage2/main/IMAGE/IMAGE_d25dc67eff9b71a6c22285b5e717268b_f3023977f29e7d36c64d63d6e4a460b8_e081908a46427e99cb06307dc61d99e7.jpg",
    "type" : "image/jpeg",
    "bitrate" : 0,
    "duration" : 0,
    "title" : null,
    "properties" : null,
    "alternate" : [ {
      "href" : "https://i115.ntcdntempv3.com/data/images/54748/927938/015-84393b9.jpg?data=net",
      "type" : "image/jpeg",
      "bitrate" : 0,
      "duration" : 0,
      "title" : null,
      "properties" : null,
      "alternate" : null
    } ]
  }, {
    "href" : "https://raw.githubusercontent.com/quetcccd/comic_storage2/main/IMAGE/IMAGE_d25dc67eff9b71a6c22285b5e717268b_f3023977f29e7d36c64d63d6e4a460b8_954badf31dfc3f50809f86f289077ce5.jpg",
    "type" : "image/jpeg",
    "bitrate" : 0,
    "duration" : 0,
    "title" : null,
    "properties" : null,
    "alternate" : [ {
      "href" : "https://i115.ntcdntempv3.com/data/images/54748/927938/016-ad7f0ff.jpg?data=net",
      "type" : "image/jpeg",
      "bitrate" : 0,
      "duration" : 0,
      "title" : null,
      "properties" : null,
      "alternate" : null
    } ]
  }, {
    "href" : "https://raw.githubusercontent.com/quetcccd/comic_storage2/main/IMAGE/IMAGE_d25dc67eff9b71a6c22285b5e717268b_f3023977f29e7d36c64d63d6e4a460b8_850770885a8fe5df56717eaa7faddf4f.jpg",
    "type" : "image/jpeg",
    "bitrate" : 0,
    "duration" : 0,
    "title" : null,
    "properties" : null,
    "alternate" : [ {
      "href" : "https://i115.ntcdntempv3.com/data/images/54748/927938/017-37a601c.jpg?data=net",
      "type" : "image/jpeg",
      "bitrate" : 0,
      "duration" : 0,
      "title" : null,
      "properties" : null,
      "alternate" : null
    } ]
  }, {
    "href" : "https://raw.githubusercontent.com/quetcccd/comic_storage2/main/IMAGE/IMAGE_d25dc67eff9b71a6c22285b5e717268b_f3023977f29e7d36c64d63d6e4a460b8_f6fb37b7aebed3ec3a2283ecfc9c66b5.jpg",
    "type" : "image/jpeg",
    "bitrate" : 0,
    "duration" : 0,
    "title" : null,
    "properties" : null,
    "alternate" : [ {
      "href" : "https://i115.ntcdntempv3.com/data/images/54748/927938/018-4e7e8d9.jpg?data=net",
      "type" : "image/jpeg",
      "bitrate" : 0,
      "duration" : 0,
      "title" : null,
      "properties" : null,
      "alternate" : null
    } ]
  }, {
    "href" : "https://raw.githubusercontent.com/quetcccd/comic_storage2/main/IMAGE/IMAGE_d25dc67eff9b71a6c22285b5e717268b_f3023977f29e7d36c64d63d6e4a460b8_88a24b5cc2454822ae3b42c5f2c5586e.jpg",
    "type" : "image/jpeg",
    "bitrate" : 0,
    "duration" : 0,
    "title" : null,
    "properties" : null,
    "alternate" : [ {
      "href" : "https://i115.ntcdntempv3.com/data/images/54748/927938/019-8dfab4f.jpg?data=net",
      "type" : "image/jpeg",
      "bitrate" : 0,
      "duration" : 0,
      "title" : null,
      "properties" : null,
      "alternate" : null
    } ]
  }, {
    "href" : "https://raw.githubusercontent.com/quetcccd/comic_storage2/main/IMAGE/IMAGE_d25dc67eff9b71a6c22285b5e717268b_f3023977f29e7d36c64d63d6e4a460b8_1ec66480fcf136ef59cd2584ed1f4213.jpg",
    "type" : "image/jpeg",
    "bitrate" : 0,
    "duration" : 0,
    "title" : null,
    "properties" : null,
    "alternate" : [ {
      "href" : "https://i115.ntcdntempv3.com/data/images/54748/927938/020-1724b70.jpg?data=net",
      "type" : "image/jpeg",
      "bitrate" : 0,
      "duration" : 0,
      "title" : null,
      "properties" : null,
      "alternate" : null
    } ]
  }, {
    "href" : "https://raw.githubusercontent.com/quetcccd/comic_storage2/main/IMAGE/IMAGE_d25dc67eff9b71a6c22285b5e717268b_f3023977f29e7d36c64d63d6e4a460b8_2675b445554a8e5c16a45d64f22c280d.jpg",
    "type" : "image/jpeg",
    "bitrate" : 0,
    "duration" : 0,
    "title" : null,
    "properties" : null,
    "alternate" : [ {
      "href" : "https://i115.ntcdntempv3.com/data/images/54748/927938/021-4b555df.jpg?data=net",
      "type" : "image/jpeg",
      "bitrate" : 0,
      "duration" : 0,
      "title" : null,
      "properties" : null,
      "alternate" : null
    } ]
  }, {
    "href" : "https://raw.githubusercontent.com/quetcccd/comic_storage2/main/IMAGE/IMAGE_d25dc67eff9b71a6c22285b5e717268b_f3023977f29e7d36c64d63d6e4a460b8_8cfb1f3c4bc55133a977284acc212f5b.jpg",
    "type" : "image/jpeg",
    "bitrate" : 0,
    "duration" : 0,
    "title" : null,
    "properties" : null,
    "alternate" : [ {
      "href" : "https://i115.ntcdntempv3.com/data/images/54748/927938/022-81aede1.jpg?data=net",
      "type" : "image/jpeg",
      "bitrate" : 0,
      "duration" : 0,
      "title" : null,
      "properties" : null,
      "alternate" : null
    } ]
  }, {
    "href" : "https://raw.githubusercontent.com/quetcccd/comic_storage2/main/IMAGE/IMAGE_d25dc67eff9b71a6c22285b5e717268b_f3023977f29e7d36c64d63d6e4a460b8_46b41dc99221171da8f8b6dd74505a53.jpg",
    "type" : "image/jpeg",
    "bitrate" : 0,
    "duration" : 0,
    "title" : null,
    "properties" : null,
    "alternate" : [ {
      "href" : "https://i115.ntcdntempv3.com/data/images/54748/927938/023-a7fd9ea.jpg?data=net",
      "type" : "image/jpeg",
      "bitrate" : 0,
      "duration" : 0,
      "title" : null,
      "properties" : null,
      "alternate" : null
    } ]
  }, {
    "href" : "https://raw.githubusercontent.com/quetcccd/comic_storage2/main/IMAGE/IMAGE_d25dc67eff9b71a6c22285b5e717268b_f3023977f29e7d36c64d63d6e4a460b8_07cf09d942eb57900a2af32b9a720ecf.jpg",
    "type" : "image/jpeg",
    "bitrate" : 0,
    "duration" : 0,
    "title" : null,
    "properties" : null,
    "alternate" : [ {
      "href" : "https://i115.ntcdntempv3.com/data/images/54748/927938/024-fb3b754.jpg?data=net",
      "type" : "image/jpeg",
      "bitrate" : 0,
      "duration" : 0,
      "title" : null,
      "properties" : null,
      "alternate" : null
    } ]
  }, {
    "href" : "https://raw.githubusercontent.com/quetcccd/comic_storage2/main/IMAGE/IMAGE_d25dc67eff9b71a6c22285b5e717268b_f3023977f29e7d36c64d63d6e4a460b8_63d7d9351bf5eb1628eea982217270b2.jpg",
    "type" : "image/jpeg",
    "bitrate" : 0,
    "duration" : 0,
    "title" : null,
    "properties" : null,
    "alternate" : [ {
      "href" : "https://i115.ntcdntempv3.com/data/images/54748/927938/025-e6493c3.jpg?data=net",
      "type" : "image/jpeg",
      "bitrate" : 0,
      "duration" : 0,
      "title" : null,
      "properties" : null,
      "alternate" : null
    } ]
  }, {
    "href" : "https://raw.githubusercontent.com/quetcccd/comic_storage2/main/IMAGE/IMAGE_d25dc67eff9b71a6c22285b5e717268b_f3023977f29e7d36c64d63d6e4a460b8_a0e3e48efee257e57b86661cdbfadf76.jpg",
    "type" : "image/jpeg",
    "bitrate" : 0,
    "duration" : 0,
    "title" : null,
    "properties" : null,
    "alternate" : [ {
      "href" : "https://i115.ntcdntempv3.com/data/images/54748/927938/026-448e27b.jpg?data=net",
      "type" : "image/jpeg",
      "bitrate" : 0,
      "duration" : 0,
      "title" : null,
      "properties" : null,
      "alternate" : null
    } ]
  }, {
    "href" : "https://raw.githubusercontent.com/quetcccd/comic_storage2/main/IMAGE/IMAGE_d25dc67eff9b71a6c22285b5e717268b_f3023977f29e7d36c64d63d6e4a460b8_794b12ccc193bac4437d598005f6b437.jpg",
    "type" : "image/jpeg",
    "bitrate" : 0,
    "duration" : 0,
    "title" : null,
    "properties" : null,
    "alternate" : [ {
      "href" : "https://i115.ntcdntempv3.com/data/images/54748/927938/027-3d1b04a.jpg?data=net",
      "type" : "image/jpeg",
      "bitrate" : 0,
      "duration" : 0,
      "title" : null,
      "properties" : null,
      "alternate" : null
    } ]
  }, {
    "href" : "https://raw.githubusercontent.com/quetcccd/comic_storage2/main/IMAGE/IMAGE_d25dc67eff9b71a6c22285b5e717268b_f3023977f29e7d36c64d63d6e4a460b8_188862f66db0a36826f1893e37a4e371.jpg",
    "type" : "image/jpeg",
    "bitrate" : 0,
    "duration" : 0,
    "title" : null,
    "properties" : null,
    "alternate" : [ {
      "href" : "https://i115.ntcdntempv3.com/data/images/54748/927938/028-8d6fd39.jpg?data=net",
      "type" : "image/jpeg",
      "bitrate" : 0,
      "duration" : 0,
      "title" : null,
      "properties" : null,
      "alternate" : null
    } ]
  }, {
    "href" : "https://raw.githubusercontent.com/quetcccd/comic_storage2/main/IMAGE/IMAGE_d25dc67eff9b71a6c22285b5e717268b_f3023977f29e7d36c64d63d6e4a460b8_f56d3faeb657dd291aeaa2784421a6c2.jpg",
    "type" : "image/jpeg",
    "bitrate" : 0,
    "duration" : 0,
    "title" : null,
    "properties" : null,
    "alternate" : [ {
      "href" : "https://i115.ntcdntempv3.com/data/images/54748/927938/029-751cfc9.jpg?data=net",
      "type" : "image/jpeg",
      "bitrate" : 0,
      "duration" : 0,
      "title" : null,
      "properties" : null,
      "alternate" : null
    } ]
  }, {
    "href" : "https://raw.githubusercontent.com/quetcccd/comic_storage2/main/IMAGE/IMAGE_d25dc67eff9b71a6c22285b5e717268b_f3023977f29e7d36c64d63d6e4a460b8_c4baa09110cf5fc281d6cdea8bd00ae6.jpg",
    "type" : "image/jpeg",
    "bitrate" : 0,
    "duration" : 0,
    "title" : null,
    "properties" : null,
    "alternate" : [ {
      "href" : "https://i115.ntcdntempv3.com/data/images/54748/927938/030-ebe60d0.jpg?data=net",
      "type" : "image/jpeg",
      "bitrate" : 0,
      "duration" : 0,
      "title" : null,
      "properties" : null,
      "alternate" : null
    } ]
  }, {
    "href" : "https://raw.githubusercontent.com/quetcccd/comic_storage2/main/IMAGE/IMAGE_d25dc67eff9b71a6c22285b5e717268b_f3023977f29e7d36c64d63d6e4a460b8_80913905dcf798bbc2016790661d36de.jpg",
    "type" : "image/jpeg",
    "bitrate" : 0,
    "duration" : 0,
    "title" : null,
    "properties" : null,
    "alternate" : [ {
      "href" : "https://i115.ntcdntempv3.com/data/images/54748/927938/031-f611dfe.jpg?data=net",
      "type" : "image/jpeg",
      "bitrate" : 0,
      "duration" : 0,
      "title" : null,
      "properties" : null,
      "alternate" : null
    } ]
  }, {
    "href" : "https://raw.githubusercontent.com/quetcccd/comic_storage2/main/IMAGE/IMAGE_d25dc67eff9b71a6c22285b5e717268b_f3023977f29e7d36c64d63d6e4a460b8_5227647977a6620e036e89300555b1cf.jpg",
    "type" : "image/jpeg",
    "bitrate" : 0,
    "duration" : 0,
    "title" : null,
    "properties" : null,
    "alternate" : [ {
      "href" : "https://i115.ntcdntempv3.com/data/images/54748/927938/032-d4843c4.jpg?data=net",
      "type" : "image/jpeg",
      "bitrate" : 0,
      "duration" : 0,
      "title" : null,
      "properties" : null,
      "alternate" : null
    } ]
  }, {
    "href" : "https://raw.githubusercontent.com/quetcccd/comic_storage2/main/IMAGE/IMAGE_d25dc67eff9b71a6c22285b5e717268b_f3023977f29e7d36c64d63d6e4a460b8_85f2b63fd47c2eeec80d098b155b1462.jpg",
    "type" : "image/jpeg",
    "bitrate" : 0,
    "duration" : 0,
    "title" : null,
    "properties" : null,
    "alternate" : [ {
      "href" : "https://i115.ntcdntempv3.com/data/images/54748/927938/033-2a52f4d.jpg?data=net",
      "type" : "image/jpeg",
      "bitrate" : 0,
      "duration" : 0,
      "title" : null,
      "properties" : null,
      "alternate" : null
    } ]
  }, {
    "href" : "https://raw.githubusercontent.com/quetcccd/comic_storage2/main/IMAGE/IMAGE_d25dc67eff9b71a6c22285b5e717268b_f3023977f29e7d36c64d63d6e4a460b8_ba2fa4b2d623a7b560805e76c9565f42.jpg",
    "type" : "image/jpeg",
    "bitrate" : 0,
    "duration" : 0,
    "title" : null,
    "properties" : null,
    "alternate" : [ {
      "href" : "https://i115.ntcdntempv3.com/data/images/54748/927938/034-a6aa947.jpg?data=net",
      "type" : "image/jpeg",
      "bitrate" : 0,
      "duration" : 0,
      "title" : null,
      "properties" : null,
      "alternate" : null
    } ]
  }, {
    "href" : "https://raw.githubusercontent.com/quetcccd/comic_storage2/main/IMAGE/IMAGE_d25dc67eff9b71a6c22285b5e717268b_f3023977f29e7d36c64d63d6e4a460b8_d53f5051a01ddf1cfab9d67293366e66.jpg",
    "type" : "image/jpeg",
    "bitrate" : 0,
    "duration" : 0,
    "title" : null,
    "properties" : null,
    "alternate" : [ {
      "href" : "https://i115.ntcdntempv3.com/data/images/54748/927938/035-41975df.jpg?data=net",
      "type" : "image/jpeg",
      "bitrate" : 0,
      "duration" : 0,
      "title" : null,
      "properties" : null,
      "alternate" : null
    } ]
  }, {
    "href" : "https://raw.githubusercontent.com/quetcccd/comic_storage2/main/IMAGE/IMAGE_d25dc67eff9b71a6c22285b5e717268b_f3023977f29e7d36c64d63d6e4a460b8_9a62898dd228f70800954621374c497f.jpg",
    "type" : "image/jpeg",
    "bitrate" : 0,
    "duration" : 0,
    "title" : null,
    "properties" : null,
    "alternate" : [ {
      "href" : "https://i115.ntcdntempv3.com/data/images/54748/927938/036-12888fe.jpg?data=net",
      "type" : "image/jpeg",
      "bitrate" : 0,
      "duration" : 0,
      "title" : null,
      "properties" : null,
      "alternate" : null
    } ]
  }, {
    "href" : "https://raw.githubusercontent.com/quetcccd/comic_storage2/main/IMAGE/IMAGE_d25dc67eff9b71a6c22285b5e717268b_f3023977f29e7d36c64d63d6e4a460b8_b6956569277dfbba564fa3e6866a1eec.jpg",
    "type" : "image/jpeg",
    "bitrate" : 0,
    "duration" : 0,
    "title" : null,
    "properties" : null,
    "alternate" : [ {
      "href" : "https://i115.ntcdntempv3.com/data/images/54748/927938/037-7438d88.jpg?data=net",
      "type" : "image/jpeg",
      "bitrate" : 0,
      "duration" : 0,
      "title" : null,
      "properties" : null,
      "alternate" : null
    } ]
  }, {
    "href" : "https://raw.githubusercontent.com/quetcccd/comic_storage2/main/IMAGE/IMAGE_d25dc67eff9b71a6c22285b5e717268b_f3023977f29e7d36c64d63d6e4a460b8_5ff12ac308473f20a427ec4882925594.jpg",
    "type" : "image/jpeg",
    "bitrate" : 0,
    "duration" : 0,
    "title" : null,
    "properties" : null,
    "alternate" : [ {
      "href" : "https://i115.ntcdntempv3.com/data/images/54748/927938/038-f48557e.jpg?data=net",
      "type" : "image/jpeg",
      "bitrate" : 0,
      "duration" : 0,
      "title" : null,
      "properties" : null,
      "alternate" : null
    } ]
  }, {
    "href" : "https://raw.githubusercontent.com/quetcccd/comic_storage2/main/IMAGE/IMAGE_d25dc67eff9b71a6c22285b5e717268b_f3023977f29e7d36c64d63d6e4a460b8_6aef81831222cb8fe39033f0a64d1ff1.jpg",
    "type" : "image/jpeg",
    "bitrate" : 0,
    "duration" : 0,
    "title" : null,
    "properties" : null,
    "alternate" : [ {
      "href" : "https://i115.ntcdntempv3.com/data/images/54748/927938/039-163e59d.jpg?data=net",
      "type" : "image/jpeg",
      "bitrate" : 0,
      "duration" : 0,
      "title" : null,
      "properties" : null,
      "alternate" : null
    } ]
  }, {
    "href" : "https://raw.githubusercontent.com/quetcccd/comic_storage2/main/IMAGE/IMAGE_d25dc67eff9b71a6c22285b5e717268b_f3023977f29e7d36c64d63d6e4a460b8_af71703427d399940e740554a035b6ee.jpg",
    "type" : "image/jpeg",
    "bitrate" : 0,
    "duration" : 0,
    "title" : null,
    "properties" : null,
    "alternate" : [ {
      "href" : "https://i115.ntcdntempv3.com/data/images/54748/927938/040-058d99b.jpg?data=net",
      "type" : "image/jpeg",
      "bitrate" : 0,
      "duration" : 0,
      "title" : null,
      "properties" : null,
      "alternate" : null
    } ]
  }, {
    "href" : "https://raw.githubusercontent.com/quetcccd/comic_storage2/main/IMAGE/IMAGE_d25dc67eff9b71a6c22285b5e717268b_f3023977f29e7d36c64d63d6e4a460b8_3412d5d7c2dde0aaf9cfdbc391bfbcfc.jpg",
    "type" : "image/jpeg",
    "bitrate" : 0,
    "duration" : 0,
    "title" : null,
    "properties" : null,
    "alternate" : [ {
      "href" : "https://i115.ntcdntempv3.com/data/images/54748/927938/041-3424254.jpg?data=net",
      "type" : "image/jpeg",
      "bitrate" : 0,
      "duration" : 0,
      "title" : null,
      "properties" : null,
      "alternate" : null
    } ]
  }, {
    "href" : "https://raw.githubusercontent.com/quetcccd/comic_storage2/main/IMAGE/IMAGE_d25dc67eff9b71a6c22285b5e717268b_f3023977f29e7d36c64d63d6e4a460b8_f837cd111c26c00c13269ed229b67228.jpg",
    "type" : "image/jpeg",
    "bitrate" : 0,
    "duration" : 0,
    "title" : null,
    "properties" : null,
    "alternate" : [ {
      "href" : "https://i115.ntcdntempv3.com/data/images/54748/927938/042-d9c1c7b.jpg?data=net",
      "type" : "image/jpeg",
      "bitrate" : 0,
      "duration" : 0,
      "title" : null,
      "properties" : null,
      "alternate" : null
    } ]
  }, {
    "href" : "https://raw.githubusercontent.com/quetcccd/comic_storage2/main/IMAGE/IMAGE_d25dc67eff9b71a6c22285b5e717268b_f3023977f29e7d36c64d63d6e4a460b8_5b88eed8108f77f89a6b30d7dbf8309b.jpg",
    "type" : "image/jpeg",
    "bitrate" : 0,
    "duration" : 0,
    "title" : null,
    "properties" : null,
    "alternate" : [ {
      "href" : "https://i115.ntcdntempv3.com/data/images/54748/927938/043-68e3546.jpg?data=net",
      "type" : "image/jpeg",
      "bitrate" : 0,
      "duration" : 0,
      "title" : null,
      "properties" : null,
      "alternate" : null
    } ]
  }, {
    "href" : "https://raw.githubusercontent.com/quetcccd/comic_storage2/main/IMAGE/IMAGE_d25dc67eff9b71a6c22285b5e717268b_f3023977f29e7d36c64d63d6e4a460b8_acc0d4653a459637eeb81808d4ea9c69.jpg",
    "type" : "image/jpeg",
    "bitrate" : 0,
    "duration" : 0,
    "title" : null,
    "properties" : null,
    "alternate" : [ {
      "href" : "https://i115.ntcdntempv3.com/data/images/54748/927938/044-688a530.jpg?data=net",
      "type" : "image/jpeg",
      "bitrate" : 0,
      "duration" : 0,
      "title" : null,
      "properties" : null,
      "alternate" : null
    } ]
  }, {
    "href" : "https://raw.githubusercontent.com/quetcccd/comic_storage2/main/IMAGE/IMAGE_d25dc67eff9b71a6c22285b5e717268b_f3023977f29e7d36c64d63d6e4a460b8_a3de98e88ba8b2640f5170d8613438be.jpg",
    "type" : "image/jpeg",
    "bitrate" : 0,
    "duration" : 0,
    "title" : null,
    "properties" : null,
    "alternate" : [ {
      "href" : "https://i115.ntcdntempv3.com/data/images/54748/927938/045-34ec14c.jpg?data=net",
      "type" : "image/jpeg",
      "bitrate" : 0,
      "duration" : 0,
      "title" : null,
      "properties" : null,
      "alternate" : null
    } ]
  }, {
    "href" : "https://raw.githubusercontent.com/quetcccd/comic_storage2/main/IMAGE/IMAGE_d25dc67eff9b71a6c22285b5e717268b_f3023977f29e7d36c64d63d6e4a460b8_5bfeda3f12921316cf7cd1c1ae4ef475.jpg",
    "type" : "image/jpeg",
    "bitrate" : 0,
    "duration" : 0,
    "title" : null,
    "properties" : null,
    "alternate" : [ {
      "href" : "https://i115.ntcdntempv3.com/data/images/54748/927938/046-83a597d.jpg?data=net",
      "type" : "image/jpeg",
      "bitrate" : 0,
      "duration" : 0,
      "title" : null,
      "properties" : null,
      "alternate" : null
    } ]
  }, {
    "href" : "https://raw.githubusercontent.com/quetcccd/comic_storage2/main/IMAGE/IMAGE_d25dc67eff9b71a6c22285b5e717268b_f3023977f29e7d36c64d63d6e4a460b8_82f1602a876769e489d40be128e5b319.jpg",
    "type" : "image/jpeg",
    "bitrate" : 0,
    "duration" : 0,
    "title" : null,
    "properties" : null,
    "alternate" : [ {
      "href" : "https://i115.ntcdntempv3.com/data/images/54748/927938/047-6ee774f.jpg?data=net",
      "type" : "image/jpeg",
      "bitrate" : 0,
      "duration" : 0,
      "title" : null,
      "properties" : null,
      "alternate" : null
    } ]
  }, {
    "href" : "https://raw.githubusercontent.com/quetcccd/comic_storage2/main/IMAGE/IMAGE_d25dc67eff9b71a6c22285b5e717268b_f3023977f29e7d36c64d63d6e4a460b8_fa974c8955b21a94f7d4ad6e62c0625d.jpg",
    "type" : "image/jpeg",
    "bitrate" : 0,
    "duration" : 0,
    "title" : null,
    "properties" : null,
    "alternate" : [ {
      "href" : "https://i115.ntcdntempv3.com/data/images/54748/927938/048-fa68bfa.jpg?data=net",
      "type" : "image/jpeg",
      "bitrate" : 0,
      "duration" : 0,
      "title" : null,
      "properties" : null,
      "alternate" : null
    } ]
  }, {
    "href" : "https://raw.githubusercontent.com/quetcccd/comic_storage2/main/IMAGE/IMAGE_d25dc67eff9b71a6c22285b5e717268b_f3023977f29e7d36c64d63d6e4a460b8_f40fe77181658d3fa756062114c7253e.jpg",
    "type" : "image/jpeg",
    "bitrate" : 0,
    "duration" : 0,
    "title" : null,
    "properties" : null,
    "alternate" : [ {
      "href" : "https://i115.ntcdntempv3.com/data/images/54748/927938/049-966bfb3.jpg?data=net",
      "type" : "image/jpeg",
      "bitrate" : 0,
      "duration" : 0,
      "title" : null,
      "properties" : null,
      "alternate" : null
    } ]
  }, {
    "href" : "https://raw.githubusercontent.com/quetcccd/comic_storage2/main/IMAGE/IMAGE_d25dc67eff9b71a6c22285b5e717268b_f3023977f29e7d36c64d63d6e4a460b8_dea6fbe4cc8221a0ca71be35e2363a2c.jpg",
    "type" : "image/jpeg",
    "bitrate" : 0,
    "duration" : 0,
    "title" : null,
    "properties" : null,
    "alternate" : [ {
      "href" : "https://i115.ntcdntempv3.com/data/images/54748/927938/050-044536d.jpg?data=net",
      "type" : "image/jpeg",
      "bitrate" : 0,
      "duration" : 0,
      "title" : null,
      "properties" : null,
      "alternate" : null
    } ]
  }, {
    "href" : "https://raw.githubusercontent.com/quetcccd/comic_storage2/main/IMAGE/IMAGE_d25dc67eff9b71a6c22285b5e717268b_f3023977f29e7d36c64d63d6e4a460b8_b0e2c9e38dfb86ae8625ca35f718d789.jpg",
    "type" : "image/jpeg",
    "bitrate" : 0,
    "duration" : 0,
    "title" : null,
    "properties" : null,
    "alternate" : [ {
      "href" : "https://i115.ntcdntempv3.com/data/images/54748/927938/051-4bb978f.jpg?data=net",
      "type" : "image/jpeg",
      "bitrate" : 0,
      "duration" : 0,
      "title" : null,
      "properties" : null,
      "alternate" : null
    } ]
  }, {
    "href" : "https://raw.githubusercontent.com/quetcccd/comic_storage2/main/IMAGE/IMAGE_d25dc67eff9b71a6c22285b5e717268b_f3023977f29e7d36c64d63d6e4a460b8_875f272e9ff243a0714c0d84c4fc2d7d.jpg",
    "type" : "image/jpeg",
    "bitrate" : 0,
    "duration" : 0,
    "title" : null,
    "properties" : null,
    "alternate" : [ {
      "href" : "https://i115.ntcdntempv3.com/data/images/54748/927938/052-79b5c31.jpg?data=net",
      "type" : "image/jpeg",
      "bitrate" : 0,
      "duration" : 0,
      "title" : null,
      "properties" : null,
      "alternate" : null
    } ]
  }, {
    "href" : "https://raw.githubusercontent.com/quetcccd/comic_storage2/main/IMAGE/IMAGE_d25dc67eff9b71a6c22285b5e717268b_f3023977f29e7d36c64d63d6e4a460b8_8805ea6bdcac7b930b4bd4e5e802e63e.jpg",
    "type" : "image/jpeg",
    "bitrate" : 0,
    "duration" : 0,
    "title" : null,
    "properties" : null,
    "alternate" : [ {
      "href" : "https://i115.ntcdntempv3.com/data/images/54748/927938/053-9509a66.jpg?data=net",
      "type" : "image/jpeg",
      "bitrate" : 0,
      "duration" : 0,
      "title" : null,
      "properties" : null,
      "alternate" : null
    } ]
  }, {
    "href" : "https://raw.githubusercontent.com/quetcccd/comic_storage2/main/IMAGE/IMAGE_d25dc67eff9b71a6c22285b5e717268b_f3023977f29e7d36c64d63d6e4a460b8_3fc2cc6d6abc81cb8d77011fe0c2b5c5.jpg",
    "type" : "image/jpeg",
    "bitrate" : 0,
    "duration" : 0,
    "title" : null,
    "properties" : null,
    "alternate" : [ {
      "href" : "https://i115.ntcdntempv3.com/data/images/54748/927938/054-202f092.jpg?data=net",
      "type" : "image/jpeg",
      "bitrate" : 0,
      "duration" : 0,
      "title" : null,
      "properties" : null,
      "alternate" : null
    } ]
  }, {
    "href" : "https://raw.githubusercontent.com/quetcccd/comic_storage2/main/IMAGE/IMAGE_d25dc67eff9b71a6c22285b5e717268b_f3023977f29e7d36c64d63d6e4a460b8_b4230edd1b8a872597e5655e68cbb510.jpg",
    "type" : "image/jpeg",
    "bitrate" : 0,
    "duration" : 0,
    "title" : null,
    "properties" : null,
    "alternate" : [ {
      "href" : "https://i115.ntcdntempv3.com/data/images/54748/927938/055-e187e2a.jpg?data=net",
      "type" : "image/jpeg",
      "bitrate" : 0,
      "duration" : 0,
      "title" : null,
      "properties" : null,
      "alternate" : null
    } ]
  }, {
    "href" : "https://raw.githubusercontent.com/quetcccd/comic_storage2/main/IMAGE/IMAGE_d25dc67eff9b71a6c22285b5e717268b_f3023977f29e7d36c64d63d6e4a460b8_f88ee581a7c4a6c0b2baed3f617f07ae.jpg",
    "type" : "image/jpeg",
    "bitrate" : 0,
    "duration" : 0,
    "title" : null,
    "properties" : null,
    "alternate" : [ {
      "href" : "https://i115.ntcdntempv3.com/data/images/54748/927938/056-15989bf.jpg?data=net",
      "type" : "image/jpeg",
      "bitrate" : 0,
      "duration" : 0,
      "title" : null,
      "properties" : null,
      "alternate" : null
    } ]
  }, {
    "href" : "https://raw.githubusercontent.com/quetcccd/comic_storage2/main/IMAGE/IMAGE_d25dc67eff9b71a6c22285b5e717268b_f3023977f29e7d36c64d63d6e4a460b8_4479ccccc23f690c4123a82c69ae0733.jpg",
    "type" : "image/jpeg",
    "bitrate" : 0,
    "duration" : 0,
    "title" : null,
    "properties" : null,
    "alternate" : [ {
      "href" : "https://i115.ntcdntempv3.com/data/images/54748/927938/057-8f2f216.jpg?data=net",
      "type" : "image/jpeg",
      "bitrate" : 0,
      "duration" : 0,
      "title" : null,
      "properties" : null,
      "alternate" : null
    } ]
  }, {
    "href" : "https://raw.githubusercontent.com/quetcccd/comic_storage2/main/IMAGE/IMAGE_d25dc67eff9b71a6c22285b5e717268b_f3023977f29e7d36c64d63d6e4a460b8_e0d8d41a76d2192fd5cd822f862df5b4.jpg",
    "type" : "image/jpeg",
    "bitrate" : 0,
    "duration" : 0,
    "title" : null,
    "properties" : null,
    "alternate" : [ {
      "href" : "https://i115.ntcdntempv3.com/data/images/54748/927938/058-86cabf8.jpg?data=net",
      "type" : "image/jpeg",
      "bitrate" : 0,
      "duration" : 0,
      "title" : null,
      "properties" : null,
      "alternate" : null
    } ]
  }, {
    "href" : "https://raw.githubusercontent.com/quetcccd/comic_storage2/main/IMAGE/IMAGE_d25dc67eff9b71a6c22285b5e717268b_f3023977f29e7d36c64d63d6e4a460b8_192ecaadd6a4db880f25c5ba2cd2883e.jpg",
    "type" : "image/jpeg",
    "bitrate" : 0,
    "duration" : 0,
    "title" : null,
    "properties" : null,
    "alternate" : [ {
      "href" : "https://i115.ntcdntempv3.com/data/images/54748/927938/059-30c2fdb.jpg?data=net",
      "type" : "image/jpeg",
      "bitrate" : 0,
      "duration" : 0,
      "title" : null,
      "properties" : null,
      "alternate" : null
    } ]
  }, {
    "href" : "https://raw.githubusercontent.com/quetcccd/comic_storage2/main/IMAGE/IMAGE_d25dc67eff9b71a6c22285b5e717268b_f3023977f29e7d36c64d63d6e4a460b8_9d62dcd84e67af948265e8aa9f948def.jpg",
    "type" : "image/jpeg",
    "bitrate" : 0,
    "duration" : 0,
    "title" : null,
    "properties" : null,
    "alternate" : [ {
      "href" : "https://i115.ntcdntempv3.com/data/images/54748/927938/060-bcf99c3.jpg?data=net",
      "type" : "image/jpeg",
      "bitrate" : 0,
      "duration" : 0,
      "title" : null,
      "properties" : null,
      "alternate" : null
    } ]
  }, {
    "href" : "https://raw.githubusercontent.com/quetcccd/comic_storage2/main/IMAGE/IMAGE_d25dc67eff9b71a6c22285b5e717268b_f3023977f29e7d36c64d63d6e4a460b8_2f163a0e7438ff840686a33e7f98bf9d.jpg",
    "type" : "image/jpeg",
    "bitrate" : 0,
    "duration" : 0,
    "title" : null,
    "properties" : null,
    "alternate" : [ {
      "href" : "https://i115.ntcdntempv3.com/data/images/54748/927938/061-7d1827b.jpg?data=net",
      "type" : "image/jpeg",
      "bitrate" : 0,
      "duration" : 0,
      "title" : null,
      "properties" : null,
      "alternate" : null
    } ]
  }, {
    "href" : "https://raw.githubusercontent.com/quetcccd/comic_storage2/main/IMAGE/IMAGE_d25dc67eff9b71a6c22285b5e717268b_f3023977f29e7d36c64d63d6e4a460b8_b06c210de81b00890a683e7b991b0ad8.jpg",
    "type" : "image/jpeg",
    "bitrate" : 0,
    "duration" : 0,
    "title" : null,
    "properties" : null,
    "alternate" : [ {
      "href" : "https://i115.ntcdntempv3.com/data/images/54748/927938/062-560cfb8.jpg?data=net",
      "type" : "image/jpeg",
      "bitrate" : 0,
      "duration" : 0,
      "title" : null,
      "properties" : null,
      "alternate" : null
    } ]
  }, {
    "href" : "https://raw.githubusercontent.com/quetcccd/comic_storage2/main/IMAGE/IMAGE_d25dc67eff9b71a6c22285b5e717268b_f3023977f29e7d36c64d63d6e4a460b8_c8fb6240e4ea2a7c1a1b56433c41ae21.jpg",
    "type" : "image/jpeg",
    "bitrate" : 0,
    "duration" : 0,
    "title" : null,
    "properties" : null,
    "alternate" : [ {
      "href" : "https://i115.ntcdntempv3.com/data/images/54748/927938/063-24ba392.jpg?data=net",
      "type" : "image/jpeg",
      "bitrate" : 0,
      "duration" : 0,
      "title" : null,
      "properties" : null,
      "alternate" : null
    } ]
  }, {
    "href" : "https://raw.githubusercontent.com/quetcccd/comic_storage2/main/IMAGE/IMAGE_d25dc67eff9b71a6c22285b5e717268b_f3023977f29e7d36c64d63d6e4a460b8_a9a7884c18062053719424087da06e3f.jpg",
    "type" : "image/jpeg",
    "bitrate" : 0,
    "duration" : 0,
    "title" : null,
    "properties" : null,
    "alternate" : [ {
      "href" : "https://i115.ntcdntempv3.com/data/images/54748/927938/064-6e90a23.jpg?data=net",
      "type" : "image/jpeg",
      "bitrate" : 0,
      "duration" : 0,
      "title" : null,
      "properties" : null,
      "alternate" : null
    } ]
  }, {
    "href" : "https://raw.githubusercontent.com/quetcccd/comic_storage2/main/IMAGE/IMAGE_d25dc67eff9b71a6c22285b5e717268b_f3023977f29e7d36c64d63d6e4a460b8_9d5d96eb598cfa5a9042fbec67df73ee.jpg",
    "type" : "image/jpeg",
    "bitrate" : 0,
    "duration" : 0,
    "title" : null,
    "properties" : null,
    "alternate" : [ {
      "href" : "https://i115.ntcdntempv3.com/data/images/54748/927938/065-dd471a8.jpg?data=net",
      "type" : "image/jpeg",
      "bitrate" : 0,
      "duration" : 0,
      "title" : null,
      "properties" : null,
      "alternate" : null
    } ]
  }, {
    "href" : "https://raw.githubusercontent.com/quetcccd/comic_storage2/main/IMAGE/IMAGE_d25dc67eff9b71a6c22285b5e717268b_f3023977f29e7d36c64d63d6e4a460b8_a29288001f0367e7eaf1428d2881e06c.jpg",
    "type" : "image/jpeg",
    "bitrate" : 0,
    "duration" : 0,
    "title" : null,
    "properties" : null,
    "alternate" : [ {
      "href" : "https://i115.ntcdntempv3.com/data/images/54748/927938/066-a7a3c81.jpg?data=net",
      "type" : "image/jpeg",
      "bitrate" : 0,
      "duration" : 0,
      "title" : null,
      "properties" : null,
      "alternate" : null
    } ]
  }, {
    "href" : "https://raw.githubusercontent.com/quetcccd/comic_storage2/main/IMAGE/IMAGE_d25dc67eff9b71a6c22285b5e717268b_f3023977f29e7d36c64d63d6e4a460b8_134a00df68708d13aea933c957c614fa.jpg",
    "type" : "image/jpeg",
    "bitrate" : 0,
    "duration" : 0,
    "title" : null,
    "properties" : null,
    "alternate" : [ {
      "href" : "https://i115.ntcdntempv3.com/data/images/54748/927938/067-a2e1f4c.jpg?data=net",
      "type" : "image/jpeg",
      "bitrate" : 0,
      "duration" : 0,
      "title" : null,
      "properties" : null,
      "alternate" : null
    } ]
  }, {
    "href" : "https://raw.githubusercontent.com/quetcccd/comic_storage2/main/IMAGE/IMAGE_d25dc67eff9b71a6c22285b5e717268b_f3023977f29e7d36c64d63d6e4a460b8_c3a2874a29832fa4a1957c00d3dee7ca.jpg",
    "type" : "image/jpeg",
    "bitrate" : 0,
    "duration" : 0,
    "title" : null,
    "properties" : null,
    "alternate" : [ {
      "href" : "https://i115.ntcdntempv3.com/data/images/54748/927938/068-14e3681.jpg?data=net",
      "type" : "image/jpeg",
      "bitrate" : 0,
      "duration" : 0,
      "title" : null,
      "properties" : null,
      "alternate" : null
    } ]
  }, {
    "href" : "https://raw.githubusercontent.com/quetcccd/comic_storage2/main/IMAGE/IMAGE_d25dc67eff9b71a6c22285b5e717268b_f3023977f29e7d36c64d63d6e4a460b8_b3d9c3464483975f3fe1e95443cfce2b.jpg",
    "type" : "image/jpeg",
    "bitrate" : 0,
    "duration" : 0,
    "title" : null,
    "properties" : null,
    "alternate" : [ {
      "href" : "https://i115.ntcdntempv3.com/data/images/54748/927938/069-d92925e.jpg?data=net",
      "type" : "image/jpeg",
      "bitrate" : 0,
      "duration" : 0,
      "title" : null,
      "properties" : null,
      "alternate" : null
    } ]
  }, {
    "href" : "https://raw.githubusercontent.com/quetcccd/comic_storage2/main/IMAGE/IMAGE_d25dc67eff9b71a6c22285b5e717268b_f3023977f29e7d36c64d63d6e4a460b8_1ffb21426189304635ff2ffe338b2e92.jpg",
    "type" : "image/jpeg",
    "bitrate" : 0,
    "duration" : 0,
    "title" : null,
    "properties" : null,
    "alternate" : [ {
      "href" : "https://i115.ntcdntempv3.com/data/images/54748/927938/070-2aed033.jpg?data=net",
      "type" : "image/jpeg",
      "bitrate" : 0,
      "duration" : 0,
      "title" : null,
      "properties" : null,
      "alternate" : null
    } ]
  }, {
    "href" : "https://raw.githubusercontent.com/quetcccd/comic_storage2/main/IMAGE/IMAGE_d25dc67eff9b71a6c22285b5e717268b_f3023977f29e7d36c64d63d6e4a460b8_5bae7c5a971e5e9cac1fdf5a1dcef4ca.jpg",
    "type" : "image/jpeg",
    "bitrate" : 0,
    "duration" : 0,
    "title" : null,
    "properties" : null,
    "alternate" : [ {
      "href" : "https://i115.ntcdntempv3.com/data/images/54748/927938/071-392047c.jpg?data=net",
      "type" : "image/jpeg",
      "bitrate" : 0,
      "duration" : 0,
      "title" : null,
      "properties" : null,
      "alternate" : null
    } ]
  }, {
    "href" : "https://raw.githubusercontent.com/quetcccd/comic_storage2/main/IMAGE/IMAGE_d25dc67eff9b71a6c22285b5e717268b_f3023977f29e7d36c64d63d6e4a460b8_392674d9173c5f65ddf1f26e7e203cc9.jpg",
    "type" : "image/jpeg",
    "bitrate" : 0,
    "duration" : 0,
    "title" : null,
    "properties" : null,
    "alternate" : [ {
      "href" : "https://i115.ntcdntempv3.com/data/images/54748/927938/072-c5da846.jpg?data=net",
      "type" : "image/jpeg",
      "bitrate" : 0,
      "duration" : 0,
      "title" : null,
      "properties" : null,
      "alternate" : null
    } ]
  }, {
    "href" : "https://raw.githubusercontent.com/quetcccd/comic_storage2/main/IMAGE/IMAGE_d25dc67eff9b71a6c22285b5e717268b_f3023977f29e7d36c64d63d6e4a460b8_4b045ec886d95e0d4a5c9176d1be2dcc.jpg",
    "type" : "image/jpeg",
    "bitrate" : 0,
    "duration" : 0,
    "title" : null,
    "properties" : null,
    "alternate" : [ {
      "href" : "https://i115.ntcdntempv3.com/data/images/54748/927938/073-fdccdf6.jpg?data=net",
      "type" : "image/jpeg",
      "bitrate" : 0,
      "duration" : 0,
      "title" : null,
      "properties" : null,
      "alternate" : null
    } ]
  }, {
    "href" : "https://raw.githubusercontent.com/quetcccd/comic_storage2/main/IMAGE/IMAGE_d25dc67eff9b71a6c22285b5e717268b_f3023977f29e7d36c64d63d6e4a460b8_8d2e73e9cd9423e79166d83b290ceee9.jpg",
    "type" : "image/jpeg",
    "bitrate" : 0,
    "duration" : 0,
    "title" : null,
    "properties" : null,
    "alternate" : [ {
      "href" : "https://i115.ntcdntempv3.com/data/images/54748/927938/074-434a1fd.jpg?data=net",
      "type" : "image/jpeg",
      "bitrate" : 0,
      "duration" : 0,
      "title" : null,
      "properties" : null,
      "alternate" : null
    } ]
  }, {
    "href" : "https://raw.githubusercontent.com/quetcccd/comic_storage2/main/IMAGE/IMAGE_d25dc67eff9b71a6c22285b5e717268b_f3023977f29e7d36c64d63d6e4a460b8_05aaa0140f8ab820c109fede9e96ddf0.jpg",
    "type" : "image/jpeg",
    "bitrate" : 0,
    "duration" : 0,
    "title" : null,
    "properties" : null,
    "alternate" : [ {
      "href" : "https://i115.ntcdntempv3.com/data/images/54748/927938/075-e4b4cc3.jpg?data=net",
      "type" : "image/jpeg",
      "bitrate" : 0,
      "duration" : 0,
      "title" : null,
      "properties" : null,
      "alternate" : null
    } ]
  }, {
    "href" : "https://raw.githubusercontent.com/quetcccd/comic_storage2/main/IMAGE/IMAGE_d25dc67eff9b71a6c22285b5e717268b_f3023977f29e7d36c64d63d6e4a460b8_3a5c8d1bbfa231541678f2882d415d36.jpg",
    "type" : "image/jpeg",
    "bitrate" : 0,
    "duration" : 0,
    "title" : null,
    "properties" : null,
    "alternate" : [ {
      "href" : "https://i115.ntcdntempv3.com/data/images/54748/927938/076-8290eb2.jpg?data=net",
      "type" : "image/jpeg",
      "bitrate" : 0,
      "duration" : 0,
      "title" : null,
      "properties" : null,
      "alternate" : null
    } ]
  }, {
    "href" : "https://raw.githubusercontent.com/quetcccd/comic_storage2/main/IMAGE/IMAGE_d25dc67eff9b71a6c22285b5e717268b_f3023977f29e7d36c64d63d6e4a460b8_28bad715cdb5c1e1dbee05f950e6b6ca.jpg",
    "type" : "image/jpeg",
    "bitrate" : 0,
    "duration" : 0,
    "title" : null,
    "properties" : null,
    "alternate" : [ {
      "href" : "https://i115.ntcdntempv3.com/data/images/54748/927938/077-48eb510.jpg?data=net",
      "type" : "image/jpeg",
      "bitrate" : 0,
      "duration" : 0,
      "title" : null,
      "properties" : null,
      "alternate" : null
    } ]
  }, {
    "href" : "https://raw.githubusercontent.com/quetcccd/comic_storage2/main/IMAGE/IMAGE_d25dc67eff9b71a6c22285b5e717268b_f3023977f29e7d36c64d63d6e4a460b8_0c575fbf43f8676835e887ae209aa724.jpg",
    "type" : "image/jpeg",
    "bitrate" : 0,
    "duration" : 0,
    "title" : null,
    "properties" : null,
    "alternate" : [ {
      "href" : "https://i115.ntcdntempv3.com/data/images/54748/927938/078-59d0913.jpg?data=net",
      "type" : "image/jpeg",
      "bitrate" : 0,
      "duration" : 0,
      "title" : null,
      "properties" : null,
      "alternate" : null
    } ]
  }, {
    "href" : "https://raw.githubusercontent.com/quetcccd/comic_storage2/main/IMAGE/IMAGE_d25dc67eff9b71a6c22285b5e717268b_f3023977f29e7d36c64d63d6e4a460b8_313e044cc9b5ea80de421044f1fd199e.jpg",
    "type" : "image/jpeg",
    "bitrate" : 0,
    "duration" : 0,
    "title" : null,
    "properties" : null,
    "alternate" : [ {
      "href" : "https://i115.ntcdntempv3.com/data/images/54748/927938/079-00c202f.jpg?data=net",
      "type" : "image/jpeg",
      "bitrate" : 0,
      "duration" : 0,
      "title" : null,
      "properties" : null,
      "alternate" : null
    } ]
  }, {
    "href" : "https://raw.githubusercontent.com/quetcccd/comic_storage2/main/IMAGE/IMAGE_d25dc67eff9b71a6c22285b5e717268b_f3023977f29e7d36c64d63d6e4a460b8_b99aecc3385a14e25c1490e89dd5e4cd.jpg",
    "type" : "image/jpeg",
    "bitrate" : 0,
    "duration" : 0,
    "title" : null,
    "properties" : null,
    "alternate" : [ {
      "href" : "https://i115.ntcdntempv3.com/data/images/54748/927938/080-f971678.jpg?data=net",
      "type" : "image/jpeg",
      "bitrate" : 0,
      "duration" : 0,
      "title" : null,
      "properties" : null,
      "alternate" : null
    } ]
  }, {
    "href" : "https://raw.githubusercontent.com/quetcccd/comic_storage2/main/IMAGE/IMAGE_d25dc67eff9b71a6c22285b5e717268b_f3023977f29e7d36c64d63d6e4a460b8_de21350da22ef6766d182ffcbb00d86e.jpg",
    "type" : "image/jpeg",
    "bitrate" : 0,
    "duration" : 0,
    "title" : null,
    "properties" : null,
    "alternate" : [ {
      "href" : "https://i115.ntcdntempv3.com/data/images/54748/927938/081-5ccb25e.jpg?data=net",
      "type" : "image/jpeg",
      "bitrate" : 0,
      "duration" : 0,
      "title" : null,
      "properties" : null,
      "alternate" : null
    } ]
  }, {
    "href" : "https://raw.githubusercontent.com/quetcccd/comic_storage2/main/IMAGE/IMAGE_d25dc67eff9b71a6c22285b5e717268b_f3023977f29e7d36c64d63d6e4a460b8_b98d239d215fc77892c33eef55ac4f27.jpg",
    "type" : "image/jpeg",
    "bitrate" : 0,
    "duration" : 0,
    "title" : null,
    "properties" : null,
    "alternate" : [ {
      "href" : "https://i115.ntcdntempv3.com/data/images/54748/927938/082-6a04014.jpg?data=net",
      "type" : "image/jpeg",
      "bitrate" : 0,
      "duration" : 0,
      "title" : null,
      "properties" : null,
      "alternate" : null
    } ]
  }, {
    "href" : "https://raw.githubusercontent.com/quetcccd/comic_storage2/main/IMAGE/IMAGE_d25dc67eff9b71a6c22285b5e717268b_f3023977f29e7d36c64d63d6e4a460b8_3ffa62a9d8fb38ddf0421cd509e7255d.jpg",
    "type" : "image/jpeg",
    "bitrate" : 0,
    "duration" : 0,
    "title" : null,
    "properties" : null,
    "alternate" : [ {
      "href" : "https://i115.ntcdntempv3.com/data/images/54748/927938/083-567c2a3.jpg?data=net",
      "type" : "image/jpeg",
      "bitrate" : 0,
      "duration" : 0,
      "title" : null,
      "properties" : null,
      "alternate" : null
    } ]
  }, {
    "href" : "https://raw.githubusercontent.com/quetcccd/comic_storage2/main/IMAGE/IMAGE_d25dc67eff9b71a6c22285b5e717268b_f3023977f29e7d36c64d63d6e4a460b8_7ed2a0d8aad222f7d7503f20d375eb07.jpg",
    "type" : "image/jpeg",
    "bitrate" : 0,
    "duration" : 0,
    "title" : null,
    "properties" : null,
    "alternate" : [ {
      "href" : "https://i115.ntcdntempv3.com/data/images/54748/927938/084-b47e68c.jpg?data=net",
      "type" : "image/jpeg",
      "bitrate" : 0,
      "duration" : 0,
      "title" : null,
      "properties" : null,
      "alternate" : null
    } ]
  }, {
    "href" : "https://raw.githubusercontent.com/quetcccd/comic_storage2/main/IMAGE/IMAGE_d25dc67eff9b71a6c22285b5e717268b_f3023977f29e7d36c64d63d6e4a460b8_1e30fe1cb958c4bae5745984cf4e8a4e.jpg",
    "type" : "image/jpeg",
    "bitrate" : 0,
    "duration" : 0,
    "title" : null,
    "properties" : null,
    "alternate" : [ {
      "href" : "https://i115.ntcdntempv3.com/data/images/54748/927938/085-24a2564.jpg?data=net",
      "type" : "image/jpeg",
      "bitrate" : 0,
      "duration" : 0,
      "title" : null,
      "properties" : null,
      "alternate" : null
    } ]
  }, {
    "href" : "https://raw.githubusercontent.com/quetcccd/comic_storage2/main/IMAGE/IMAGE_d25dc67eff9b71a6c22285b5e717268b_f3023977f29e7d36c64d63d6e4a460b8_6105f565c7165611f00ad30e73549ffd.jpg",
    "type" : "image/jpeg",
    "bitrate" : 0,
    "duration" : 0,
    "title" : null,
    "properties" : null,
    "alternate" : [ {
      "href" : "https://i115.ntcdntempv3.com/data/images/54748/927938/086-e01cddb.jpg?data=net",
      "type" : "image/jpeg",
      "bitrate" : 0,
      "duration" : 0,
      "title" : null,
      "properties" : null,
      "alternate" : null
    } ]
  }, {
    "href" : "https://raw.githubusercontent.com/quetcccd/comic_storage2/main/IMAGE/IMAGE_d25dc67eff9b71a6c22285b5e717268b_f3023977f29e7d36c64d63d6e4a460b8_a5203319bd700743608f2fb5dddcbd34.jpg",
    "type" : "image/jpeg",
    "bitrate" : 0,
    "duration" : 0,
    "title" : null,
    "properties" : null,
    "alternate" : [ {
      "href" : "https://i115.ntcdntempv3.com/data/images/54748/927938/087-962adf3.jpg?data=net",
      "type" : "image/jpeg",
      "bitrate" : 0,
      "duration" : 0,
      "title" : null,
      "properties" : null,
      "alternate" : null
    } ]
  }, {
    "href" : "https://raw.githubusercontent.com/quetcccd/comic_storage2/main/IMAGE/IMAGE_d25dc67eff9b71a6c22285b5e717268b_f3023977f29e7d36c64d63d6e4a460b8_6a20bee54a7de85a4fb60ef33d412e4f.jpg",
    "type" : "image/jpeg",
    "bitrate" : 0,
    "duration" : 0,
    "title" : null,
    "properties" : null,
    "alternate" : [ {
      "href" : "https://i115.ntcdntempv3.com/data/images/54748/927938/088-745405d.jpg?data=net",
      "type" : "image/jpeg",
      "bitrate" : 0,
      "duration" : 0,
      "title" : null,
      "properties" : null,
      "alternate" : null
    } ]
  }, {
    "href" : "https://raw.githubusercontent.com/quetcccd/comic_storage2/main/IMAGE/IMAGE_d25dc67eff9b71a6c22285b5e717268b_f3023977f29e7d36c64d63d6e4a460b8_672e1c5b098e2b52f198cf84080ec375.jpg",
    "type" : "image/jpeg",
    "bitrate" : 0,
    "duration" : 0,
    "title" : null,
    "properties" : null,
    "alternate" : [ {
      "href" : "https://i115.ntcdntempv3.com/data/images/54748/927938/089-e162145.jpg?data=net",
      "type" : "image/jpeg",
      "bitrate" : 0,
      "duration" : 0,
      "title" : null,
      "properties" : null,
      "alternate" : null
    } ]
  }, {
    "href" : "https://raw.githubusercontent.com/quetcccd/comic_storage2/main/IMAGE/IMAGE_d25dc67eff9b71a6c22285b5e717268b_f3023977f29e7d36c64d63d6e4a460b8_c3abd8b799dce906a4378753b796cee6.jpg",
    "type" : "image/jpeg",
    "bitrate" : 0,
    "duration" : 0,
    "title" : null,
    "properties" : null,
    "alternate" : [ {
      "href" : "https://i115.ntcdntempv3.com/data/images/54748/927938/090-745ca50.jpg?data=net",
      "type" : "image/jpeg",
      "bitrate" : 0,
      "duration" : 0,
      "title" : null,
      "properties" : null,
      "alternate" : null
    } ]
  }, {
    "href" : "https://raw.githubusercontent.com/quetcccd/comic_storage2/main/IMAGE/IMAGE_d25dc67eff9b71a6c22285b5e717268b_f3023977f29e7d36c64d63d6e4a460b8_d8541c05a8785d92f74b9d12ea07ed47.jpg",
    "type" : "image/jpeg",
    "bitrate" : 0,
    "duration" : 0,
    "title" : null,
    "properties" : null,
    "alternate" : [ {
      "href" : "https://i115.ntcdntempv3.com/data/images/54748/927938/091-92f1175.jpg?data=net",
      "type" : "image/jpeg",
      "bitrate" : 0,
      "duration" : 0,
      "title" : null,
      "properties" : null,
      "alternate" : null
    } ]
  }, {
    "href" : "https://raw.githubusercontent.com/quetcccd/comic_storage2/main/IMAGE/IMAGE_d25dc67eff9b71a6c22285b5e717268b_f3023977f29e7d36c64d63d6e4a460b8_1b11a9ee9e27cb5077bb363c29a34d09.jpg",
    "type" : "image/jpeg",
    "bitrate" : 0,
    "duration" : 0,
    "title" : null,
    "properties" : null,
    "alternate" : [ {
      "href" : "https://i115.ntcdntempv3.com/data/images/54748/927938/092-0e7ef56.jpg?data=net",
      "type" : "image/jpeg",
      "bitrate" : 0,
      "duration" : 0,
      "title" : null,
      "properties" : null,
      "alternate" : null
    } ]
  }, {
    "href" : "https://raw.githubusercontent.com/quetcccd/comic_storage2/main/IMAGE/IMAGE_d25dc67eff9b71a6c22285b5e717268b_f3023977f29e7d36c64d63d6e4a460b8_ac6614952653fc6b9359a75946bb6a0a.jpg",
    "type" : "image/jpeg",
    "bitrate" : 0,
    "duration" : 0,
    "title" : null,
    "properties" : null,
    "alternate" : [ {
      "href" : "https://i115.ntcdntempv3.com/data/images/54748/927938/093-0b1e372.jpg?data=net",
      "type" : "image/jpeg",
      "bitrate" : 0,
      "duration" : 0,
      "title" : null,
      "properties" : null,
      "alternate" : null
    } ]
  }, {
    "href" : "https://raw.githubusercontent.com/quetcccd/comic_storage2/main/IMAGE/IMAGE_d25dc67eff9b71a6c22285b5e717268b_f3023977f29e7d36c64d63d6e4a460b8_4dbf902c5617fc76d17ea1d60d2044e4.jpg",
    "type" : "image/jpeg",
    "bitrate" : 0,
    "duration" : 0,
    "title" : null,
    "properties" : null,
    "alternate" : [ {
      "href" : "https://i115.ntcdntempv3.com/data/images/54748/927938/094-e274584.jpg?data=net",
      "type" : "image/jpeg",
      "bitrate" : 0,
      "duration" : 0,
      "title" : null,
      "properties" : null,
      "alternate" : null
    } ]
  }, {
    "href" : "https://raw.githubusercontent.com/quetcccd/comic_storage2/main/IMAGE/IMAGE_d25dc67eff9b71a6c22285b5e717268b_f3023977f29e7d36c64d63d6e4a460b8_18559d0b444d9fa8f8ddd191c3ad9ad6.jpg",
    "type" : "image/jpeg",
    "bitrate" : 0,
    "duration" : 0,
    "title" : null,
    "properties" : null,
    "alternate" : [ {
      "href" : "https://i115.ntcdntempv3.com/data/images/54748/927938/095-b1225ce.jpg?data=net",
      "type" : "image/jpeg",
      "bitrate" : 0,
      "duration" : 0,
      "title" : null,
      "properties" : null,
      "alternate" : null
    } ]
  }, {
    "href" : "https://raw.githubusercontent.com/quetcccd/comic_storage2/main/IMAGE/IMAGE_d25dc67eff9b71a6c22285b5e717268b_f3023977f29e7d36c64d63d6e4a460b8_906f27815eec4f45081777a32a4af510.jpg",
    "type" : "image/jpeg",
    "bitrate" : 0,
    "duration" : 0,
    "title" : null,
    "properties" : null,
    "alternate" : [ {
      "href" : "https://i115.ntcdntempv3.com/data/images/54748/927938/096-9b5215f.jpg?data=net",
      "type" : "image/jpeg",
      "bitrate" : 0,
      "duration" : 0,
      "title" : null,
      "properties" : null,
      "alternate" : null
    } ]
  }, {
    "href" : "https://raw.githubusercontent.com/quetcccd/comic_storage2/main/IMAGE/IMAGE_d25dc67eff9b71a6c22285b5e717268b_f3023977f29e7d36c64d63d6e4a460b8_3cba1de1887fea529fd99831f2091f91.jpg",
    "type" : "image/jpeg",
    "bitrate" : 0,
    "duration" : 0,
    "title" : null,
    "properties" : null,
    "alternate" : [ {
      "href" : "https://i115.ntcdntempv3.com/data/images/54748/927938/097-28623ee.jpg?data=net",
      "type" : "image/jpeg",
      "bitrate" : 0,
      "duration" : 0,
      "title" : null,
      "properties" : null,
      "alternate" : null
    } ]
  }, {
    "href" : "https://raw.githubusercontent.com/quetcccd/comic_storage2/main/IMAGE/IMAGE_d25dc67eff9b71a6c22285b5e717268b_f3023977f29e7d36c64d63d6e4a460b8_d62d5863996617896fb2ce4dda5803ea.jpg",
    "type" : "image/jpeg",
    "bitrate" : 0,
    "duration" : 0,
    "title" : null,
    "properties" : null,
    "alternate" : [ {
      "href" : "https://i115.ntcdntempv3.com/data/images/54748/927938/098-2ee033d.jpg?data=net",
      "type" : "image/jpeg",
      "bitrate" : 0,
      "duration" : 0,
      "title" : null,
      "properties" : null,
      "alternate" : null
    } ]
  }, {
    "href" : "https://raw.githubusercontent.com/quetcccd/comic_storage2/main/IMAGE/IMAGE_d25dc67eff9b71a6c22285b5e717268b_f3023977f29e7d36c64d63d6e4a460b8_ef08eb4821560b0bf66adb14e608f37d.jpg",
    "type" : "image/jpeg",
    "bitrate" : 0,
    "duration" : 0,
    "title" : null,
    "properties" : null,
    "alternate" : [ {
      "href" : "https://i115.ntcdntempv3.com/data/images/54748/927938/099-1c58b28.jpg?data=net",
      "type" : "image/jpeg",
      "bitrate" : 0,
      "duration" : 0,
      "title" : null,
      "properties" : null,
      "alternate" : null
    } ]
  }, {
    "href" : "https://raw.githubusercontent.com/quetcccd/comic_storage2/main/IMAGE/IMAGE_d25dc67eff9b71a6c22285b5e717268b_f3023977f29e7d36c64d63d6e4a460b8_d75fe068a6695baf265aa378827e2590.jpg",
    "type" : "image/jpeg",
    "bitrate" : 0,
    "duration" : 0,
    "title" : null,
    "properties" : null,
    "alternate" : [ {
      "href" : "https://i115.ntcdntempv3.com/data/images/54748/927938/100-d292376.jpg?data=net",
      "type" : "image/jpeg",
      "bitrate" : 0,
      "duration" : 0,
      "title" : null,
      "properties" : null,
      "alternate" : null
    } ]
  }, {
    "href" : "https://raw.githubusercontent.com/quetcccd/comic_storage2/main/IMAGE/IMAGE_d25dc67eff9b71a6c22285b5e717268b_f3023977f29e7d36c64d63d6e4a460b8_dee6a2069d75846b185399bdf68066c3.jpg",
    "type" : "image/jpeg",
    "bitrate" : 0,
    "duration" : 0,
    "title" : null,
    "properties" : null,
    "alternate" : [ {
      "href" : "https://i115.ntcdntempv3.com/data/images/54748/927938/101-98dd1ef.jpg?data=net",
      "type" : "image/jpeg",
      "bitrate" : 0,
      "duration" : 0,
      "title" : null,
      "properties" : null,
      "alternate" : null
    } ]
  }, {
    "href" : "https://raw.githubusercontent.com/quetcccd/comic_storage2/main/IMAGE/IMAGE_d25dc67eff9b71a6c22285b5e717268b_f3023977f29e7d36c64d63d6e4a460b8_84321dc869f96dcae833983c900bffe0.jpg",
    "type" : "image/jpeg",
    "bitrate" : 0,
    "duration" : 0,
    "title" : null,
    "properties" : null,
    "alternate" : [ {
      "href" : "https://i115.ntcdntempv3.com/data/images/54748/927938/102-30f9c18.jpg?data=net",
      "type" : "image/jpeg",
      "bitrate" : 0,
      "duration" : 0,
      "title" : null,
      "properties" : null,
      "alternate" : null
    } ]
  }, {
    "href" : "https://raw.githubusercontent.com/quetcccd/comic_storage2/main/IMAGE/IMAGE_d25dc67eff9b71a6c22285b5e717268b_f3023977f29e7d36c64d63d6e4a460b8_3ee966c003d52120a32f69f89b8b16d6.jpg",
    "type" : "image/jpeg",
    "bitrate" : 0,
    "duration" : 0,
    "title" : null,
    "properties" : null,
    "alternate" : [ {
      "href" : "https://i115.ntcdntempv3.com/data/images/54748/927938/103-b6de5ec.jpg?data=net",
      "type" : "image/jpeg",
      "bitrate" : 0,
      "duration" : 0,
      "title" : null,
      "properties" : null,
      "alternate" : null
    } ]
  }, {
    "href" : "https://raw.githubusercontent.com/quetcccd/comic_storage2/main/IMAGE/IMAGE_d25dc67eff9b71a6c22285b5e717268b_f3023977f29e7d36c64d63d6e4a460b8_62de680c6053c4d54f9f233220ce953f.jpg",
    "type" : "image/jpeg",
    "bitrate" : 0,
    "duration" : 0,
    "title" : null,
    "properties" : null,
    "alternate" : [ {
      "href" : "https://i115.ntcdntempv3.com/data/images/54748/927938/104-d07e91a.jpg?data=net",
      "type" : "image/jpeg",
      "bitrate" : 0,
      "duration" : 0,
      "title" : null,
      "properties" : null,
      "alternate" : null
    } ]
  } ],
  "toc" : null,
  "@context" : "https://readium.org/webpub-manifest/context.jsonld"
}